[{"NI_ratio <= 0.5273833671399594": [{"hits_count_pro <= 1": [{"orf_len <= -0.820358061026638": [{"ratio_hits_prom <= 0.0": [{"hits_count <= -0.5428198770316959": [{"NI <= 0.541833982619119": [{"HFI_ratio <= 0.003588067589180168": [{"NI_ratio <= 0.18644067796610173": [{"HFI_normalized <= 0.4487951807228915": ["non_ess", "ess"]}, "non_ess"]}, "non_ess"]}, "non_ess"]}, "ess"]}, "non_ess"]}, {"NI_ratio <= 0.4537815126050421": [{"insertion_index <= 0.0029069767441860465": [{"orf_len <= -0.5613273698219808": ["ess", "non_ess"]}, {"NI_ratio <= 0.1493617021276596": [{"HFI_normalized <= 0.3161434977578476": [{"hits_count <= -0.8169222021376209": ["non_ess", {"HFI_normalized <= 0.2718035563082134": [{"NI <= 0.4495206816971418": [{"NI <= 0.2813405797101449": ["ess", {"NI_ratio <= 0.04826823876197495": ["ess", {"insertion_index <= 0.015915119363395226": ["non_ess", {"HFI_normalized <= 0.1522105973675329": ["non_ess", "ess"]}]}]}]}, "ess"]}, "non_ess"]}]}, "ess"]}, {"ratio_hits_prom <= 0.0": [{"orf_len <= 1.4018526056238423": [{"HFI_ratio <= 0.0018248175182481753": [{"NI <= 0.4746782608695653": [{"NI <= 0.2855618492490657": [{"NI <= 0.17576999207530944": ["ess", {"NI_ratio <= 0.2852941176470589": [{"HFI_ratio <= 0.0004153870249436504": [{"NI_ratio <= 0.2749731471535983": ["ess", "non_ess"]}, {"orf_len <= -0.7767318393500642": ["ess", "non_ess"]}]}, {"NI_ratio <= 0.32545454545454544": ["ess", {"orf_len <= 0.3493700076764982": ["ess", "non_ess"]}]}]}]}, {"insertion_index <= 0.025210084033613446": [{"reads_count <= 0.021860590623078796": ["ess", "non_ess"]}, "non_ess"]}]}, {"NI <= 0.542132155538235": [{"NI_ratio <= 0.30604838709677423": ["ess", "non_ess"]}, {"HFI_normalized <= 0.09274387313791446": [{"hits_count <= 0.3708545399880545": ["non_ess", "ess"]}, {"reads_count <= -0.1958728104277556": ["non_ess", {"reads_count <= -0.07482780103000357": ["ess", {"NI <= 0.6021026831785345": ["ess", {"hits_count <= 0.7363243067959546": ["non_ess", {"HFI_ratio <= 0.000251846571795366": ["non_ess", "ess"]}]}]}]}]}]}]}]}, {"NI_ratio <= 0.2108050847457627": ["ess", "non_ess"]}]}, {"insertion_index <= 0.009163533834586466": ["ess", {"hits_count <= 0.5079057025410171": ["non_ess", {"insertion_index <= 0.013566397078006779": [{"HFI_ratio <= 5.008035741004459e-05": ["non_ess", "ess"]}, {"NI_ratio <= 0.21978557504873286": ["ess", "non_ess"]}]}]}]}]}, {"HFI_ratio <= 0.0005895180513427863": [{"NI <= 0.4140178410609839": [{"NI_ratio <= 0.15182186234817815": ["non_ess", "ess"]}, {"reads_count <= -0.051947341936526066": ["ess", "non_ess"]}]}, {"NI_ratio <= 0.326530612244898": ["non_ess", {"insertion_index <= 0.008027522935779817": ["ess", {"orf_len <= -0.6840261182873447": ["ess", "non_ess"]}]}]}]}]}]}]}, {"hits_count <= -0.2230338310747832": [{"HFI_normalized <= 0.2356296621325143": ["ess", "non_ess"]}, {"HFI_ratio <= 0.0007170172084130017": [{"orf_len <= 2.132591818706454": ["non_ess", "ess"]}, "ess"]}]}]}]}, {"HFI_ratio <= 0.00021655187813037768": [{"NI <= 0.4697738655547717": [{"hits_count <= 1.55863128211373": ["ess", "non_ess"]}, "non_ess"]}, {"NI_ratio <= 0.2382920110192837": [{"ratio_hits_prom <= 1.6": [{"reads_count <= -0.2359136138413412": ["ess", {"orf_len <= 0.0957925941814127": [{"ratio_hits_prom <= 0.65625": ["ess", "non_ess"]}, "ess"]}]}, {"ratio_hits_prom <= 8.0": ["ess", "non_ess"]}]}, {"NI <= 0.4122557090700837": ["non_ess", {"NI <= 0.4570725572433209": [{"orf_len <= -0.2723036512146791": ["non_ess", "ess"]}, {"hits_count <= -0.1773501102237957": [{"insertion_index <= 0.02985074626865672": ["non_ess", {"insertion_index <= 0.04270462633451957": ["ess", "non_ess"]}]}, "non_ess"]}]}]}]}]}]}, {"ratio_hits_prom <= 0.0": [{"orf_len <= -0.7712785616404925": ["non_ess", {"NI_ratio <= 0.6910621761658033": [{"NI <= 0.23556763285024154": ["ess", {"HFI_ratio <= 0.00043395374504590377": [{"orf_len <= 1.3900371705864367": [{"HFI_ratio <= 0.00019933625887654085": ["non_ess", {"HFI_normalized <= 0.2886023004531196": ["ess", "non_ess"]}]}, "non_ess"]}, {"HFI_normalized <= 0.21948051948051947": ["non_ess", {"insertion_index <= 0.016347501167678656": ["non_ess", {"hits_count <= -0.4514524353297208": [{"HFI_ratio <= 0.000457678775977745": ["non_ess", "ess"]}, "non_ess"]}]}]}]}]}, {"NI <= 0.19988002117273426": [{"reads_count <= -0.2394194906379224": ["ess", {"reads_count <= -0.2279792610911837": ["non_ess", {"insertion_index <= 0.010299324106855488": [{"NI_ratio <= 0.9355707986281234": [{"NI_ratio <= 0.7415413533834587": ["ess", "non_ess"]}, "ess"]}, "non_ess"]}]}]}, {"hits_count <= -0.1316663893728082": [{"NI_ratio <= 1.0294117647058825": [{"HFI_ratio <= 0.000295608508219243": ["ess", {"NI_ratio <= 0.8091954022988505": ["non_ess", {"HFI_ratio <= 0.0004992250591402235": ["non_ess", {"insertion_index <= 0.012332439678284185": ["ess", {"hits_count <= -0.4057687144787333": ["ess", "non_ess"]}]}]}]}]}, "non_ess"]}, "non_ess"]}]}]}]}, {"NI <= 0.3773289141381801": [{"hits_count_pro <= 3": [{"ratio_hits_prom <= 2.7777777777777777": [{"HFI_normalized <= 0.5125739644970414": ["non_ess", {"ratio_hits_prom <= 1.1333333333333333": ["non_ess", {"HFI_ratio <= 0.002336448598130841": [{"orf_len <= -0.558600730967195": ["ess", "non_ess"]}, "non_ess"]}]}]}, {"NI <= 0.2952884422730145": [{"insertion_index <= 0.007805724197745012": ["ess", "non_ess"]}, "ess"]}]}, "non_ess"]}, "non_ess"]}]}]}, {"NI_ratio <= 0.4604554865424431": [{"HFI_ratio <= 0.00033558644325971064": [{"reads_count <= -0.12612431415892894": [{"NI <= 0.2784447212691655": ["ess", {"hits_count_pro <= 0": [{"hits_count <= -0.08598266852182067": ["ess", {"hits_count <= 0.05106849403114188": ["non_ess", "ess"]}]}, {"ratio_hits_prom <= 0.75": ["non_ess", "ess"]}]}]}, {"NI_ratio <= 0.2286061711506308": [{"NI <= 0.21177315058013832": ["non_ess", "ess"]}, {"insertion_index <= 0.031186440677966106": [{"NI_ratio <= 0.4214659685863874": [{"HFI_ratio <= 0.00013171412765733257": ["ess", {"HFI_normalized <= 0.13892078071182548": [{"insertion_index <= 0.027554535017221583": ["non_ess", {"hits_count <= 1.1931615153058301": ["ess", "non_ess"]}]}, {"hits_count <= 0.14243593573311691": ["ess", {"reads_count <= 0.013003638715926209": [{"NI_ratio <= 0.3220390720390721": ["ess", "non_ess"]}, "ess"]}]}]}]}, "non_ess"]}, "non_ess"]}]}]}, {"NI_ratio <= 0.3322553191489361": [{"orf_len <= -0.16596473587803034": [{"NI <= 1.3762029670291491": [{"NI_ratio <= 0.1968800430338892": [{"HFI_ratio <= 0.0007063596229566878": [{"ratio_hits_prom <= 1.7142857142857142": [{"HFI_ratio <= 0.0005297866877281252": [{"insertion_index <= 0.014693171996542784": [{"HFI_ratio <= 0.0003569047544250954": ["ess", {"orf_len <= -0.6349466189011992": ["ess", "non_ess"]}]}, "ess"]}, {"reads_count <= -0.2386814113123264": ["ess", {"ratio_hits_prom <= 0.9333333333333332": ["non_ess", "ess"]}]}]}, "non_ess"]}, {"HFI_ratio <= 0.0007932510034943343": ["ess", {"ratio_hits_prom <= 1.1153846153846154": [{"HFI_ratio <= 0.0014646377853114404": [{"insertion_index <= 0.009881422924901186": ["ess", {"insertion_index <= 0.014423076923076926": ["non_ess", {"reads_count <= -0.23019349906797185": ["ess", {"HFI_ratio <= 0.0012799331893030266": ["non_ess", "ess"]}]}]}]}, {"hits_count_pro <= 0": [{"reads_count <= -0.2381278518181293": ["ess", "non_ess"]}, "non_ess"]}]}, {"reads_count <= -0.2285328205853807": [{"HFI_normalized <= 0.5215311004784688": ["non_ess", "ess"]}, "ess"]}]}]}]}, {"hits_count_pro <= 2": [{"NI_ratio <= 0.20397249809014514": ["non_ess", {"insertion_index <= 0.015570934256055362": [{"NI_ratio <= 0.25130434782608696": ["ess", "non_ess"]}, {"HFI_normalized <= 0.3275217932752179": [{"HFI_normalized <= 0.23091603053435114": [{"reads_count <= -0.2252114636201985": ["non_ess", "ess"]}, "non_ess"]}, "ess"]}]}]}, "non_ess"]}]}, "non_ess"]}, {"NI_ratio <= 0.2415662650602409": [{"insertion_index <= 0.016574585635359115": [{"orf_len <= 0.008540150828265012": [{"NI_ratio <= 0.23228803716608595": ["ess", "non_ess"]}, "non_ess"]}, "ess"]}, "ess"]}]}, {"hits_count_pro <= 2": [{"insertion_index <= 0.0065491183879093215": ["non_ess", {"HFI_ratio <= 0.0003704759190652608": ["non_ess", {"HFI_ratio <= 0.002648171500630517": [{"insertion_index <= 0.01457725947521866": ["ess", {"HFI_ratio <= 0.0010272930194805195": [{"hits_count <= -0.1773501102237957": ["non_ess", {"HFI_normalized <= 0.09720534629404616": ["non_ess", "ess"]}]}, "ess"]}]}, "non_ess"]}]}]}, "non_ess"]}]}]}, {"ratio_hits_prom <= 0.0": [{"insertion_index <= 0.01104815864022663": [{"HFI_ratio <= 0.00019512182948473326": [{"NI_ratio <= 0.6404907975460123": ["ess", "non_ess"]}, {"reads_count <= -0.2388659311437254": [{"insertion_index <= 0.0014903129657228018": ["non_ess", "ess"]}, {"reads_count <= -0.22447338429460245": ["non_ess", {"hits_count <= -0.7712384812866334": [{"orf_len <= -0.6594863685942719": [{"HFI_normalized <= 0.5765472312703583": ["non_ess", "ess"]}, "ess"]}, {"HFI_ratio <= 0.000295608508219243": [{"hits_count <= -0.26871755192577074": ["ess", "non_ess"]}, "non_ess"]}]}]}]}]}, {"NI_ratio <= 0.6982674076495587": [{"HFI_ratio <= 0.0010553564317005175": [{"HFI_ratio <= 0.0007697532261716097": [{"reads_count <= -0.172254272008682": ["non_ess", {"reads_count <= -0.14310013864763807": ["ess", {"HFI_ratio <= 0.0003345641653102024": [{"orf_len <= 1.3900371705864367": [{"HFI_normalized <= 0.2886023004531196": [{"NI_ratio <= 0.4804953560371518": ["non_ess", "ess"]}, "non_ess"]}, {"NI <= 0.3489587218303645": ["non_ess", "ess"]}]}, "non_ess"]}]}]}, {"hits_count <= -0.1316663893728082": ["ess", "non_ess"]}]}, {"NI_ratio <= 0.6417112299465239": ["non_ess", "ess"]}]}, {"HFI_normalized <= 0.2007255139056832": ["non_ess", {"HFI_ratio <= 0.0008346972176759411": [{"hits_count <= -0.4514524353297208": [{"insertion_index <= 0.011049723756906077": ["non_ess", "ess"]}, {"HFI_normalized <= 0.2540073982737361": ["non_ess", "ess"]}]}, {"orf_len <= 0.3411900911121405": ["non_ess", {"orf_len <= 0.39299622935307205": ["ess", "non_ess"]}]}]}]}]}]}, {"hits_count_pro <= 2": [{"insertion_index <= 0.011229646266142616": [{"HFI_ratio <= 7.383350296024945e-05": ["ess", {"ratio_hits_prom <= 3.8": [{"NI_ratio <= 0.6845238095238095": [{"insertion_index <= 0.006691449814126393": ["ess", {"NI_ratio <= 0.4795580110497237": ["ess", "non_ess"]}]}, "non_ess"]}, "ess"]}]}, {"ratio_hits_prom <= 8.0": [{"NI_ratio <= 0.601948051948052": [{"NI_ratio <= 0.5989974937343359": [{"NI <= 0.4570725572433209": [{"reads_count <= -0.10342837489685046": ["non_ess", {"reads_count <= -0.10084509725726427": ["ess", {"NI <= 0.4101462628123921": ["non_ess", "ess"]}]}]}, "non_ess"]}, "ess"]}, {"orf_len <= -0.8803441158319271": [{"NI_ratio <= 0.8333333333333335": [{"ratio_hits_prom <= 1.5333333333333334": ["non_ess", "ess"]}, "non_ess"]}, "non_ess"]}]}, "ess"]}]}, {"NI_ratio <= 0.512937062937063": [{"NI_ratio <= 0.5074074074074073": ["non_ess", "ess"]}, "non_ess"]}]}]}]}, {"HFI_ratio <= 0.0002883561993744714": [{"hits_count_pro <= 2": [{"NI_ratio <= 0.658887987012987": [{"reads_count <= 1.026202032927902": [{"HFI_ratio <= 6.555728179752678e-05": ["ess", {"NI_ratio <= 0.4343750000000001": [{"orf_len <= 2.2661971225909614": [{"orf_len <= 1.7317759070529315": [{"HFI_ratio <= 0.000251846571795366": [{"HFI_ratio <= 0.00024036947622546451": [{"HFI_normalized <= 0.12027972027972028": ["ess", {"hits_count <= -0.5885035978826834": ["ess", {"hits_count <= 0.5535894233920046": [{"HFI_ratio <= 0.0001939664130222276": [{"NI <= 0.3564947945789068": [{"NI_ratio <= 0.09448051948051947": [{"insertion_index <= 0.008457511075312122": ["ess", "non_ess"]}, {"reads_count <= -0.11597572343198327": [{"insertion_index <= 0.013338564142801098": [{"HFI_ratio <= 0.00018191381872848108": ["ess", "non_ess"]}, "non_ess"]}, "ess"]}]}, "ess"]}, "ess"]}, {"NI_ratio <= 0.106312292358804": ["ess", {"reads_count <= 0.0945614041942896": ["non_ess", "ess"]}]}]}]}]}, "non_ess"]}, "ess"]}, "ess"]}, {"HFI_ratio <= 0.00012666933893052776": ["ess", "non_ess"]}]}, {"insertion_index <= 0.010901883052527254": ["ess", {"orf_len <= 0.8919711397788853": [{"NI <= 0.25599355916030536": ["non_ess", "ess"]}, {"NI <= 0.4754012093029655": ["non_ess", "ess"]}]}]}]}]}, "non_ess"]}, {"HFI_ratio <= 0.0001413771325580712": [{"NI_ratio <= 0.9193397695421986": ["non_ess", "ess"]}, "non_ess"]}]}, "non_ess"]}, {"hits_count_pro <= 0": [{"hits_count <= 0.005384773180154362": [{"NI_ratio <= 0.4405762304921969": [{"HFI_ratio <= 0.003042192958882021": [{"orf_len <= 0.3057437859999243": [{"NI <= 0.5704423628783367": [{"NI <= 0.3842970201082129": [{"orf_len <= 0.1994048706632756": [{"HFI_ratio <= 0.00045807113323860304": [{"HFI_normalized <= 0.2234910277324633": ["ess", {"HFI_normalized <= 0.2479435957696827": ["non_ess", {"orf_len <= -0.1305184307658141": [{"reads_count <= -0.22742570159698666": ["non_ess", "ess"]}, "non_ess"]}]}]}, {"hits_count <= -0.6798710395846584": [{"NI_ratio <= 0.0": ["ess", {"insertion_index <= 0.015313935681470138": [{"reads_count <= -0.21653903154444493": [{"NI <= 0.13582616707616707": ["ess", "non_ess"]}, "ess"]}, "non_ess"]}]}, "ess"]}]}, "non_ess"]}, {"NI_ratio <= 0.3352226720647773": ["ess", "non_ess"]}]}, {"hits_count <= -0.36008499362774576": [{"HFI_ratio <= 0.002209944751381216": ["non_ess", "ess"]}, "ess"]}]}, "ess"]}, {"insertion_index <= 0.029953917050691243": ["non_ess", "ess"]}]}, {"insertion_index <= 0.002183406113537118": [{"insertion_index <= 0.000859106529209622": ["non_ess", "ess"]}, {"NI <= 0.2257682194576351": [{"HFI_ratio <= 0.00032495800071122885": ["ess", {"HFI_ratio <= 0.0035858206406666213": [{"NI_ratio <= 1.4223602484472049": [{"hits_count <= -1.091024527243546": ["ess", {"HFI_ratio <= 0.001677757103661421": [{"insertion_index <= 0.0035545023696682467": ["non_ess", {"insertion_index <= 0.006081668114682885": ["ess", {"NI_ratio <= 0.7047619047619048": ["non_ess", {"HFI_ratio <= 0.0009092562284051649": ["ess", "non_ess"]}]}]}]}, "non_ess"]}]}, "non_ess"]}, "non_ess"]}]}, {"HFI_ratio <= 0.0012814210072452671": [{"orf_len <= -0.23140406839289115": [{"insertion_index <= 0.016282225237449117": [{"HFI_normalized <= 0.2224797219003476": ["ess", "non_ess"]}, {"HFI_normalized <= 0.198813056379822": ["non_ess", {"NI_ratio <= 0.5866666666666667": [{"HFI_normalized <= 0.2306701030927835": ["non_ess", "ess"]}, "ess"]}]}]}, "non_ess"]}, {"HFI_ratio <= 0.002317795518928664": ["non_ess", {"HFI_ratio <= 0.002493765586034913": ["ess", "non_ess"]}]}]}]}]}]}, {"insertion_index <= 0.05074626865671642": [{"orf_len <= -0.16051145816845866": [{"NI_ratio <= 0.3469827586206897": ["ess", "non_ess"]}, {"HFI_normalized <= 0.2880835380835381": [{"NI_ratio <= 0.12080250426863975": ["ess", "non_ess"]}, {"orf_len <= 0.837438362683168": ["non_ess", "ess"]}]}]}, "ess"]}]}, {"NI_ratio <= 0.27244582043343657": [{"orf_len <= -0.3186565117460388": [{"ratio_hits_prom <= 1.026315789473684": ["non_ess", {"NI <= 0.3085687903970453": [{"orf_len <= -0.4922525188340722": ["non_ess", "ess"]}, {"NI_ratio <= 0.1515919977458439": ["ess", {"orf_len <= -0.5667806475315526": [{"hits_count <= -0.8169222021376209": ["ess", "non_ess"]}, "ess"]}]}]}]}, {"hits_count <= 1.1931615153058301": ["non_ess", "ess"]}]}, {"HFI_normalized <= 0.2269736842105264": ["non_ess", {"hits_count_pro <= 2": [{"NI_ratio <= 0.8193146417445483": [{"NI <= 1.6806923726428369": [{"ratio_hits_prom <= 0.9714285714285714": [{"NI_ratio <= 0.4188405797101449": ["ess", "non_ess"]}, {"NI_ratio <= 0.6": ["non_ess", {"NI_ratio <= 0.7882930997650074": [{"HFI_ratio <= 0.0010165356465166712": [{"HFI_ratio <= 0.000741312223265799": ["non_ess", "ess"]}, "non_ess"]}, "ess"]}]}]}, "ess"]}, {"insertion_index <= 0.006329113924050633": [{"hits_count <= -1.0453408063925584": ["non_ess", "ess"]}, "non_ess"]}]}, {"hits_count_pro <= 10": ["non_ess", {"HFI_normalized <= 0.23100303951367784": ["ess", {"hits_count <= -0.9082896438395959": ["ess", "non_ess"]}]}]}]}]}]}]}]}, {"NI_ratio <= 0.5045871559633027": [{"HFI_ratio <= 0.00034118556258408": [{"reads_count <= -0.18055766442163754": [{"reads_count <= -0.201777445032524": [{"insertion_index <= 0.009994739610731194": ["ess", {"HFI_normalized <= 0.252506836827712": ["non_ess", "ess"]}]}, "ess"]}, {"NI_ratio <= 0.3428571428571429": [{"insertion_index <= 0.031506849315068496": [{"ratio_hits_prom <= 1.6666666666666663": [{"NI <= 0.2826198461234958": [{"insertion_index <= 0.009828009828009828": [{"reads_count <= -0.053608020419117185": [{"HFI_normalized <= 0.2090506640432858": ["ess", {"NI <= 0.14771577421648527": ["non_ess", "ess"]}]}, "non_ess"]}, {"NI_ratio <= 0.3174715909090909": ["non_ess", "ess"]}]}, {"insertion_index <= 0.02057467186945725": [{"reads_count <= -0.0674470077740431": ["ess", {"hits_count <= 0.7363243067959546": ["non_ess", "ess"]}]}, {"insertion_index <= 0.02837489251934652": [{"orf_len <= 1.2055346080792595": [{"NI <= 0.7851771641701256": ["non_ess", "ess"]}, "ess"]}, "ess"]}]}]}, "ess"]}, "non_ess"]}, {"insertion_index <= 0.01931415057154119": [{"NI_ratio <= 0.36504036504036497": ["non_ess", {"insertion_index <= 0.013776337115072932": [{"NI <= 0.25757582675823104": ["ess", {"insertion_index <= 0.012490440989039": [{"HFI_ratio <= 0.00012114094162392098": ["ess", "non_ess"]}, "ess"]}]}, "ess"]}]}, "non_ess"]}]}]}, {"NI_ratio <= 0.31341991341991343": [{"HFI_ratio <= 0.001736210755897377": [{"hits_count_pro <= 0": [{"orf_len <= -0.6540330908847002": ["ess", {"orf_len <= -0.6349466189011992": ["non_ess", {"reads_count <= -0.1674567563923077": [{"orf_len <= -0.6213134246272698": ["non_ess", {"orf_len <= -0.3650093722773985": [{"insertion_index <= 0.019971469329529243": ["ess", "non_ess"]}, {"orf_len <= -0.214135355645914": ["non_ess", {"hits_count <= -0.6341873187336708": ["ess", "non_ess"]}]}]}]}, {"HFI_ratio <= 0.0006681649760068031": ["ess", {"HFI_ratio <= 0.0008325248897420547": ["non_ess", "ess"]}]}]}]}]}, {"NI_ratio <= 0.15919360444907887": [{"NI <= 0.3085687903970453": [{"HFI_ratio <= 0.0006336260469045742": ["non_ess", "ess"]}, "ess"]}, {"NI_ratio <= 0.27840000000000004": ["non_ess", {"HFI_normalized <= 0.1586469747498809": ["ess", "non_ess"]}]}]}]}, {"HFI_normalized <= 0.5215311004784688": ["non_ess", {"insertion_index <= 0.005025125628140704": [{"hits_count_pro <= 0": [{"HFI_ratio <= 0.003105590062111801": ["non_ess", "ess"]}, "non_ess"]}, {"HFI_ratio <= 0.005900943163300578": [{"NI <= 0.4058562051804892": [{"insertion_index <= 0.010526315789473684": [{"HFI_normalized <= 0.6083650190114068": ["non_ess", "ess"]}, {"HFI_ratio <= 0.003686136332836428": ["non_ess", "ess"]}]}, "ess"]}, "non_ess"]}]}]}]}, {"hits_count_pro <= 0": [{"insertion_index <= 0.021398002853067047": [{"insertion_index <= 0.017482517482517484": [{"insertion_index <= 0.015319148936170212": [{"HFI_normalized <= 0.2280851063829787": ["non_ess", {"reads_count <= -0.187384898183401": ["non_ess", "ess"]}]}, "ess"]}, {"NI <= 0.3533600641539695": ["ess", "non_ess"]}]}, {"HFI_ratio <= 0.0007693024990675122": [{"NI_ratio <= 0.4201388888888889": ["non_ess", "ess"]}, "ess"]}]}, {"ratio_hits_prom <= 1.857142857142857": [{"insertion_index <= 0.011229646266142616": [{"hits_count <= -0.4057687144787333": ["non_ess", "ess"]}, "non_ess"]}, {"NI <= 0.42646194534234494": [{"HFI_normalized <= 0.33": ["ess", "non_ess"]}, {"NI_ratio <= 0.3896713615023474": ["ess", "non_ess"]}]}]}]}]}]}, {"ratio_hits_prom <= 0.0": [{"NI <= 0.09098811938568532": [{"NI_ratio <= 1.5769230769230769": ["ess", "non_ess"]}, {"NI_ratio <= 0.6910621761658033": [{"NI_ratio <= 0.6398601398601399": [{"NI <= 0.35453162456205056": [{"HFI_normalized <= 0.330166270783848": [{"reads_count <= -0.08183955462316604": ["ess", "non_ess"]}, "non_ess"]}, "non_ess"]}, {"hits_count <= 0.3708545399880545": [{"HFI_ratio <= 0.0003802077180018688": ["ess", {"orf_len <= -0.6876616367603926": ["ess", "non_ess"]}]}, "non_ess"]}]}, {"reads_count <= -0.1979025285731447": [{"NI_ratio <= 0.9158878504672898": [{"HFI_ratio <= 0.0011450701220417894": ["non_ess", {"orf_len <= -0.8230846998814239": ["non_ess", "ess"]}]}, {"HFI_normalized <= 0.5905882352941176": ["non_ess", {"NI <= 0.262676653890043": [{"HFI_ratio <= 0.0010172284717023324": ["ess", "non_ess"]}, "ess"]}]}]}, {"hits_count <= 0.2794870982860795": [{"HFI_normalized <= 0.19974226804123715": ["non_ess", {"HFI_normalized <= 0.20598648213710974": ["ess", {"reads_count <= 0.3010390955297842": [{"insertion_index <= 0.0118510158013544": [{"HFI_normalized <= 0.3404503105590062": ["non_ess", "ess"]}, "non_ess"]}, "ess"]}]}]}, "non_ess"]}]}]}]}, {"ratio_hits_prom <= 2.4": [{"HFI_normalized <= 0.6737184703010578": [{"NI_ratio <= 0.601948051948052": [{"NI_ratio <= 0.6003588516746412": ["non_ess", "ess"]}, "non_ess"]}, {"HFI_normalized <= 0.9675425038639875": [{"ratio_hits_prom <= 0.8333333333333333": [{"hits_count_pro <= 10": ["ess", "non_ess"]}, {"ratio_hits_prom <= 1.55": ["non_ess", {"hits_count_pro <= 7": ["non_ess", "ess"]}]}]}, "non_ess"]}]}, {"ratio_hits_prom <= 2.4000000000000004": [{"insertion_index <= 0.014857142857142857": ["ess", "non_ess"]}, {"ratio_hits_prom <= 3.5": ["non_ess", {"hits_count_pro <= 2": [{"NI_ratio <= 0.742997542997543": ["ess", {"NI <= 1.3630268465711504": ["non_ess", "ess"]}]}, "non_ess"]}]}]}]}]}]}, {"NI_ratio <= 0.5209471766848816": [{"ratio_hits_prom <= 0.0": [{"HFI_ratio <= 0.0005054362922106264": [{"NI <= 0.3413645428095067": [{"HFI_normalized <= 0.4544776119402985": [{"hits_count <= 1.0104266319018798": [{"reads_count <= -0.10748781118762872": [{"hits_count <= -0.4514524353297208": [{"HFI_normalized <= 0.17458677685950413": ["non_ess", {"insertion_index <= 0.009701492537313429": ["ess", {"HFI_normalized <= 0.2176628010704728": ["ess", "non_ess"]}]}]}, "ess"]}, {"insertion_index <= 0.015026660203587009": [{"reads_count <= -0.06246497232626976": ["ess", {"insertion_index <= 0.0140218878248974": ["non_ess", "ess"]}]}, "non_ess"]}]}, "ess"]}, "non_ess"]}, {"NI <= 0.5413729421696918": [{"NI_ratio <= 0.4067584480600752": [{"NI_ratio <= 0.3733770031582641": [{"HFI_ratio <= 0.0003255724649174799": [{"HFI_ratio <= 6.602531209519129e-05": ["ess", {"orf_len <= 0.7065596976534465": [{"NI <= 0.473146190570096": [{"insertion_index <= 0.01938923897237033": [{"HFI_ratio <= 9.739377823526049e-05": ["ess", {"NI <= 0.4334388740490162": ["non_ess", "ess"]}]}, "ess"]}, "non_ess"]}, "non_ess"]}]}, {"NI <= 0.3554866972967197": ["non_ess", "ess"]}]}, "ess"]}, "non_ess"]}, {"insertion_index <= 0.008778930566640064": [{"NI <= 0.5715919125138679": ["ess", "non_ess"]}, "ess"]}]}]}, {"HFI_ratio <= 0.0036101083032490976": [{"HFI_normalized <= 0.4302059496567506": [{"insertion_index <= 0.038306451612903226": [{"HFI_normalized <= 0.3654135338345865": [{"NI_ratio <= 0.325": [{"HFI_normalized <= 0.3460949464012251": [{"reads_count <= -0.22410434463180445": ["non_ess", {"NI <= 0.26391911376194443": ["ess", {"HFI_ratio <= 0.0005420777760247902": ["ess", {"reads_count <= -0.21967586867822814": ["ess", {"HFI_normalized <= 0.30124223602484473": [{"NI <= 0.6777295285359801": ["non_ess", "ess"]}, "ess"]}]}]}]}]}, "ess"]}, {"insertion_index <= 0.02092050209205021": [{"insertion_index <= 0.012779552715654952": ["non_ess", {"insertion_index <= 0.01740506329113924": ["non_ess", "ess"]}]}, "non_ess"]}]}, "non_ess"]}, "ess"]}, {"orf_len <= -0.2723036512146791": [{"hits_count <= -0.9539733646905836": [{"HFI_normalized <= 0.6586483390607102": [{"reads_count <= -0.2279792610911837": [{"NI <= 0.04658986938699057": ["non_ess", "ess"]}, "non_ess"]}, "ess"]}, "ess"]}, {"orf_len <= -0.032359431993522966": ["non_ess", "ess"]}]}]}, "non_ess"]}]}, {"hits_count_pro <= 2": [{"hits_count <= -0.4971361561807083": [{"NI_ratio <= 0.1809954751131221": [{"ratio_hits_prom <= 1.0": ["non_ess", "ess"]}, {"insertion_index <= 0.008136696501220505": [{"insertion_index <= 0.0073081607795371486": ["non_ess", "ess"]}, "non_ess"]}]}, {"NI_ratio <= 0.30487804878048785": [{"HFI_ratio <= 0.00035632460546426915": ["ess", {"NI_ratio <= 0.27602523659305994": [{"HFI_ratio <= 0.00047064045365148116": ["non_ess", {"HFI_normalized <= 0.08294062205466543": ["non_ess", "ess"]}]}, "ess"]}]}, {"reads_count <= -0.0707683647392253": [{"HFI_normalized <= 0.16540130151843818": ["non_ess", {"HFI_normalized <= 0.22998296422487224": ["ess", {"HFI_ratio <= 0.0005827505827505828": ["non_ess", "ess"]}]}]}, {"HFI_normalized <= 0.081661222585161": ["non_ess", "ess"]}]}]}]}, {"NI_ratio <= 0.30435372304353714": [{"hits_count_pro <= 3": [{"NI_ratio <= 0.20328282828282826": ["ess", {"hits_count <= 0.0967522148821294": ["non_ess", "ess"]}]}, "non_ess"]}, "non_ess"]}]}]}, {"insertion_index <= 0.02229845626072041": [{"ratio_hits_prom <= 0.0": [{"NI_ratio <= 0.6910621761658033": [{"NI_ratio <= 0.6": [{"reads_count <= -0.1890455766659921": ["ess", {"insertion_index <= 0.01776198934280639": ["non_ess", {"reads_count <= -0.1510344913977956": ["non_ess", "ess"]}]}]}, {"HFI_ratio <= 0.0006451811905263754": ["ess", {"orf_len <= -0.09779876450838372": [{"reads_count <= -0.2220746264864153": ["non_ess", "ess"]}, "non_ess"]}]}]}, {"insertion_index <= 0.014473684210526316": [{"reads_count <= -0.11357696562379613": [{"HFI_ratio <= 0.0004908777969018933": [{"reads_count <= -0.1768672677936573": ["non_ess", {"NI <= 0.23906254476692546": [{"insertion_index <= 0.009057225195553726": ["ess", "non_ess"]}, "ess"]}]}, {"hits_count <= -0.8169222021376209": [{"NI <= 0.32590129241931826": [{"insertion_index <= 0.006134969325153374": [{"HFI_normalized <= 0.8814352574102964": [{"insertion_index <= 0.001402524544179523": ["non_ess", {"NI_ratio <= 2.0": [{"hits_count <= -1.091024527243546": ["ess", {"hits_count <= -0.9082896438395959": ["non_ess", "ess"]}]}, "non_ess"]}]}, "non_ess"]}, "non_ess"]}, "ess"]}, "non_ess"]}]}, "non_ess"]}, {"orf_len <= -0.6267667023368415": [{"HFI_ratio <= 0.0037003903708523102": ["ess", "non_ess"]}, "non_ess"]}]}]}, {"ratio_hits_prom <= 3.8": [{"hits_count_pro <= 9": [{"insertion_index <= 0.007481296758104737": [{"HFI_ratio <= 0.00028657704620857965": ["ess", "non_ess"]}, "non_ess"]}, {"HFI_normalized <= 0.5443786982248521": ["non_ess", "ess"]}]}, {"ratio_hits_prom <= 4.800000000000002": [{"HFI_normalized <= 0.1903782894736842": ["ess", {"orf_len <= -0.6867527571421306": ["ess", "non_ess"]}]}, "non_ess"]}]}]}, {"NI_ratio <= 0.742997542997543": [{"ratio_hits_prom <= 0.0": [{"insertion_index <= 0.026775320139697318": [{"HFI_ratio <= 0.0002739446459128087": ["ess", "non_ess"]}, {"NI_ratio <= 0.5932203389830508": ["non_ess", "ess"]}]}, {"NI_ratio <= 0.7410852713178295": ["non_ess", "ess"]}]}, "non_ess"]}]}]}, {"NI_ratio <= 0.4677544677544678": [{"ratio_hits_prom <= 0.0": [{"hits_count_pro <= 1": [{"HFI_ratio <= 0.00013171412765733257": [{"NI_ratio <= 0.43971238938053103": [{"insertion_index <= 0.01008249312557287": [{"HFI_normalized <= 0.09899175068744273": ["non_ess", "ess"]}, "ess"]}, "non_ess"]}, {"orf_len <= 1.4345722718812726": [{"NI_ratio <= 0.3273498233215548": [{"HFI_ratio <= 0.001831107281344248": [{"NI_ratio <= 0.2869897959183673": [{"HFI_normalized <= 0.4368131868131868": [{"NI_ratio <= 0.2821969696969697": [{"HFI_ratio <= 0.00017976227743153383": ["ess", {"NI <= 0.17219321104238744": ["non_ess", {"hits_count <= 0.32517081913706697": [{"hits_count <= 0.05106849403114188": [{"HFI_ratio <= 0.001536098310291859": [{"HFI_normalized <= 0.4140558848433531": [{"hits_count <= -0.1773501102237957": [{"orf_len <= 0.251211008904207": [{"HFI_normalized <= 0.1529818496110631": ["non_ess", "ess"]}, "non_ess"]}, {"reads_count <= -0.17133167285168693": ["non_ess", "ess"]}]}, "non_ess"]}, "non_ess"]}, "ess"]}, {"HFI_normalized <= 0.13620386643233742": ["non_ess", {"insertion_index <= 0.0230505149583129": ["non_ess", "ess"]}]}]}]}]}, "non_ess"]}, {"NI <= 0.04569530710835058": [{"reads_count <= -0.23978853030072045": ["ess", "non_ess"]}, {"HFI_ratio <= 0.001481898789986773": ["ess", {"NI_ratio <= 0.0": ["non_ess", "ess"]}]}]}]}, "ess"]}, {"HFI_ratio <= 0.003686136332836428": [{"NI_ratio <= 0.16424418604651164": ["non_ess", "ess"]}, "ess"]}]}, {"HFI_ratio <= 0.0003352711088454713": [{"NI_ratio <= 0.3724642500831393": ["non_ess", "ess"]}, {"hits_count <= -0.5428198770316959": [{"HFI_ratio <= 0.0007951004620178362": [{"orf_len <= -0.4195421493731158": ["non_ess", "ess"]}, "ess"]}, {"insertion_index <= 0.030909090909090917": ["non_ess", {"reads_count <= -0.11652928292618032": ["ess", "non_ess"]}]}]}]}]}, {"insertion_index <= 0.012358664212463844": [{"NI_ratio <= 0.3062800274536719": [{"HFI_ratio <= 0.00017461148943600488": ["non_ess", "ess"]}, "ess"]}, "non_ess"]}]}]}, "non_ess"]}, {"hits_count_pro <= 1": [{"HFI_ratio <= 0.0002693111970090615": [{"HFI_normalized <= 0.0907282132908874": ["non_ess", "ess"]}, {"HFI_normalized <= 0.1659152389540126": [{"NI_ratio <= 0.046231846695883816": ["ess", "non_ess"]}, {"ratio_hits_prom <= 2.0": [{"insertion_index <= 0.033942558746736295": [{"ratio_hits_prom <= 1.5333333333333334": [{"orf_len <= -0.7003859514160601": [{"ratio_hits_prom <= 1.0": ["non_ess", "ess"]}, "ess"]}, {"reads_count <= -0.15343324920598275": ["non_ess", "ess"]}]}, "ess"]}, "ess"]}]}]}, {"reads_count <= -0.017257613633511786": [{"NI_ratio <= 0.3896713615023474": [{"ratio_hits_prom <= 5.333333333333333": [{"hits_count <= -0.2230338310747832": [{"hits_count_pro <= 4": [{"ratio_hits_prom <= 1.875": [{"ratio_hits_prom <= 1.3333333333333333": [{"HFI_ratio <= 0.0026445380272547693": [{"reads_count <= -0.201777445032524": ["non_ess", {"insertion_index <= 0.026845637583892617": ["ess", "non_ess"]}]}, "ess"]}, "ess"]}, "non_ess"]}, "non_ess"]}, "non_ess"]}, "ess"]}, "non_ess"]}, {"insertion_index <= 0.012422360248447204": ["non_ess", {"ratio_hits_prom <= 1.173913043478261": ["ess", {"NI_ratio <= 0.35166771554436754": ["ess", "non_ess"]}]}]}]}]}]}, {"NI_ratio <= 0.6441176470588236": [{"ratio_hits_prom <= 0.0": [{"HFI_ratio <= 0.00013241622665618964": ["ess", {"insertion_index <= 0.01104815864022663": [{"NI_ratio <= 0.5602968460111317": [{"HFI_normalized <= 0.2295632698768197": [{"NI_ratio <= 0.53125": ["ess", "non_ess"]}, "non_ess"]}, "ess"]}, {"hits_count <= -0.1773501102237957": [{"HFI_normalized <= 0.1942896935933148": ["ess", {"NI <= 0.2950228211258422": ["non_ess", {"HFI_ratio <= 0.0007755315440920183": [{"HFI_ratio <= 0.0003977750097850103": ["non_ess", "ess"]}, {"NI_ratio <= 0.523989898989899": [{"NI <= 0.35765018558401684": ["non_ess", "ess"]}, "non_ess"]}]}]}]}, {"NI <= 0.4086471685384341": ["non_ess", {"HFI_normalized <= 0.11940298507462685": ["non_ess", {"NI <= 0.6713135440451868": ["ess", "non_ess"]}]}]}]}]}]}, {"ratio_hits_prom <= 3.6666666666666665": [{"orf_len <= -0.8176314221718521": [{"orf_len <= -0.8612576438484258": ["non_ess", "ess"]}, "non_ess"]}, {"insertion_index <= 0.01496138996138996": ["ess", "non_ess"]}]}]}, {"hits_count_pro <= 0": [{"reads_count <= -0.11357696562379613": [{"orf_len <= -0.2750302900694649": [{"NI <= 0.32090924285475514": ["non_ess", {"NI <= 0.4270857648011204": [{"hits_count <= -0.7255547604356459": ["non_ess", "ess"]}, {"orf_len <= -0.940330170637216": ["ess", "non_ess"]}]}]}, {"orf_len <= -0.23140406839289115": ["ess", {"reads_count <= -0.1768672677936573": ["non_ess", {"hits_count <= 0.4622219816900296": [{"HFI_ratio <= 0.0006736735469165505": [{"HFI_normalized <= 0.22371064969859344": [{"NI <= 0.2561692944902718": ["ess", "non_ess"]}, "ess"]}, "non_ess"]}, "non_ess"]}]}]}]}, {"hits_count <= -0.4057687144787333": ["ess", "non_ess"]}]}, {"reads_count <= -0.1707781133574899": [{"reads_count <= -0.1709626331888889": [{"hits_count <= -0.7712384812866334": [{"HFI_normalized <= 0.31536388140161725": [{"ratio_hits_prom <= 1.375": ["non_ess", {"orf_len <= -0.7385588953830621": ["ess", "non_ess"]}]}, "non_ess"]}, "non_ess"]}, "ess"]}, "non_ess"]}]}]}]}, {"NI <= 0.3818050018122508": [{"ratio_hits_prom <= 0.0": [{"NI_ratio <= 0.7163742690058481": [{"HFI_normalized <= 0.5880195599022005": [{"orf_len <= -0.8176314221718521": ["non_ess", {"HFI_ratio <= 0.0008303019092833507": [{"NI <= 0.3489249867196019": [{"hits_count <= 0.05106849403114188": [{"HFI_ratio <= 0.0002882197829153125": [{"NI_ratio <= 0.33333333333333337": ["ess", {"NI_ratio <= 0.4996404171161453": [{"HFI_normalized <= 0.1659070191431176": ["ess", {"reads_count <= -0.1980870484045437": ["ess", "non_ess"]}]}, "ess"]}]}, {"hits_count <= -0.5428198770316959": [{"HFI_ratio <= 0.0008053258885428973": [{"reads_count <= -0.187200378352002": [{"NI <= 0.12666766601708887": [{"insertion_index <= 0.003913894324853229": ["ess", "non_ess"]}, {"orf_len <= -0.5604184902037188": ["non_ess", {"HFI_ratio <= 0.0006884638839296798": [{"insertion_index <= 0.006591957811470007": ["ess", {"reads_count <= -0.2211520273294202": ["ess", {"HFI_ratio <= 0.00035794914593139244": ["non_ess", {"NI_ratio <= 0.42831325301204815": ["non_ess", "ess"]}]}]}]}, "ess"]}]}]}, "ess"]}, "non_ess"]}, {"NI <= 0.3123013834594321": [{"orf_len <= 0.3766363962243568": [{"reads_count <= -0.18240286273562767": ["ess", {"reads_count <= -0.0310966009884377": ["non_ess", "ess"]}]}, "ess"]}, "ess"]}]}]}, {"HFI_ratio <= 0.00010882330095295372": ["ess", {"NI_ratio <= 0.2978204010462075": [{"HFI_normalized <= 0.171130276895143": [{"reads_count <= -0.11597572343198327": ["non_ess", "ess"]}, "non_ess"]}, {"HFI_ratio <= 0.0003001052382462977": ["non_ess", {"hits_count <= 0.23380337743509194": ["non_ess", "ess"]}]}]}]}]}, "ess"]}, "ess"]}]}, {"orf_len <= -0.8885240323962846": ["non_ess", {"NI <= 0.08534976857958225": [{"NI <= 0.08112335735481135": [{"HFI_ratio <= 0.002272727272727273": ["non_ess", "ess"]}, "ess"]}, "non_ess"]}]}]}, {"insertion_index <= 0.01492537313432836": [{"HFI_ratio <= 0.0007367157810520702": [{"NI <= 0.3365897318708105": [{"HFI_ratio <= 0.0005269443440923556": [{"HFI_ratio <= 0.0004761235108584286": [{"HFI_normalized <= 0.19195305951383068": [{"HFI_normalized <= 0.13890274314214462": ["ess", {"insertion_index <= 0.013822894168466522": ["non_ess", "ess"]}]}, {"hits_count <= -0.8626059229886085": ["non_ess", "ess"]}]}, "non_ess"]}, "ess"]}, "non_ess"]}, {"insertion_index <= 0.006134969325153374": [{"insertion_index <= 0.005571030640668525": [{"HFI_normalized <= 0.9220055710306406": ["non_ess", "ess"]}, "ess"]}, {"insertion_index <= 0.013948497854077254": ["non_ess", "ess"]}]}]}, "non_ess"]}]}, {"HFI_ratio <= 0.00018191381872848108": [{"NI_ratio <= 0.5021897810218978": [{"HFI_normalized <= 0.16481391976800386": ["ess", {"NI <= 0.12923362979949796": ["non_ess", {"orf_len <= 0.3439167299669264": ["non_ess", "ess"]}]}]}, {"hits_count_pro <= 1": [{"HFI_normalized <= 0.12878524190741386": ["non_ess", "ess"]}, "non_ess"]}]}, {"HFI_normalized <= 0.2107594936708861": [{"orf_len <= -0.1168852364918848": [{"orf_len <= -0.12779179191102824": ["non_ess", "ess"]}, "non_ess"]}, {"NI_ratio <= 0.35166771554436754": [{"hits_count <= -0.9996570855415712": ["non_ess", {"reads_count <= -0.21653903154444493": [{"hits_count <= -0.9539733646905836": ["ess", "non_ess"]}, {"orf_len <= 0.1257856215840572": ["ess", {"orf_len <= 0.311197063709496": ["non_ess", {"HFI_ratio <= 0.0001925166574076986": ["non_ess", "ess"]}]}]}]}]}, {"reads_count <= -0.23923497080652345": ["ess", {"insertion_index <= 0.014836795252225518": [{"hits_count <= -0.3144012727767583": ["non_ess", {"NI_ratio <= 0.4795580110497237": ["ess", "non_ess"]}]}, {"ratio_hits_prom <= 1.3461538461538465": ["non_ess", {"insertion_index <= 0.014857142857142857": ["ess", {"reads_count <= -0.12261843736234772": ["non_ess", {"NI <= 0.3485539855870598": ["ess", "non_ess"]}]}]}]}]}]}]}]}]}]}, {"NI_ratio <= 0.523989898989899": [{"insertion_index <= 0.04429783223374175": [{"hits_count_pro <= 1": [{"orf_len <= -0.7303789788187044": [{"insertion_index <= 0.029953917050691243": [{"reads_count <= -0.2368362129983363": ["ess", "non_ess"]}, {"reads_count <= -0.2252114636201985": ["non_ess", {"reads_count <= -0.16653415723531262": ["ess", {"hits_count <= -0.6341873187336708": ["ess", "non_ess"]}]}]}]}, {"NI_ratio <= 0.12962962962962962": ["ess", {"HFI_normalized <= 0.20877659574468085": [{"NI_ratio <= 0.2027707808564232": ["non_ess", {"reads_count <= -0.17483754964826814": ["non_ess", {"insertion_index <= 0.016156670746634027": ["ess", {"NI <= 0.7537741188577309": [{"orf_len <= 0.6438470039933716": [{"NI <= 0.6493199290360733": [{"insertion_index <= 0.02705749718151071": [{"orf_len <= 0.29756386943556673": [{"HFI_normalized <= 0.14217156568686262": ["non_ess", {"reads_count <= -0.15472488802577586": ["non_ess", {"NI <= 0.5406688178351422": ["ess", "non_ess"]}]}]}, "ess"]}, "ess"]}, "non_ess"]}, "non_ess"]}, "ess"]}]}]}]}, {"HFI_normalized <= 0.3009198423127464": ["ess", {"HFI_ratio <= 0.0011285817653784698": ["ess", "non_ess"]}]}]}]}]}, {"HFI_normalized <= 0.21040189125295508": ["non_ess", {"insertion_index <= 0.029684601113172542": ["non_ess", {"HFI_ratio <= 0.0008482854351961339": ["ess", "non_ess"]}]}]}]}, {"hits_count_pro <= 2": [{"orf_len <= -0.940330170637216": [{"hits_count <= -0.6798710395846584": ["ess", "non_ess"]}, "ess"]}, "non_ess"]}]}, {"hits_count_pro <= 0": [{"NI <= 0.6059850374064838": [{"NI_ratio <= 0.6767429193899782": [{"orf_len <= -0.6876616367603926": [{"reads_count <= -0.21266411508506566": ["non_ess", "ess"]}, {"orf_len <= 0.45298228415836106": ["non_ess", {"orf_len <= 1.5572710203466364": ["ess", "non_ess"]}]}]}, {"hits_count <= -0.6798710395846584": [{"HFI_ratio <= 0.0008346972176759411": ["ess", {"NI <= 0.5411835870551467": ["non_ess", "ess"]}]}, "non_ess"]}]}, "non_ess"]}, {"hits_count_pro <= 2": [{"reads_count <= -0.0720600035590184": [{"hits_count_pro <= 1": ["non_ess", {"NI_ratio <= 0.9725158562367864": [{"ratio_hits_prom <= 4.666666666666667": [{"HFI_normalized <= 0.7146974063400576": ["non_ess", "ess"]}, "ess"]}, "non_ess"]}]}, "non_ess"]}, "non_ess"]}]}]}]}, {"ratio_hits_prom <= 0.0": [{"NI_ratio <= 0.4627949183303085": [{"HFI_normalized <= 0.09142383648667313": ["ess", {"HFI_ratio <= 0.0018248175182481753": [{"orf_len <= -0.9157904209441432": ["non_ess", {"reads_count <= -0.07814915799518579": [{"reads_count <= -0.08755966939653542": [{"NI_ratio <= 0.2113997113997114": [{"NI <= 0.2998606989279874": [{"NI_ratio <= 0.2039258451472192": [{"orf_len <= -0.3650093722773985": ["ess", {"hits_count <= -0.9996570855415712": ["non_ess", {"HFI_ratio <= 0.00017680162327463715": ["ess", {"reads_count <= -0.21580095221884887": ["ess", {"insertion_index <= 0.011007911936704506": [{"hits_count <= -0.7255547604356459": [{"HFI_normalized <= 0.3030503978779841": ["ess", "non_ess"]}, "non_ess"]}, "ess"]}]}]}]}]}, "non_ess"]}, {"hits_count <= -0.26871755192577074": [{"orf_len <= -0.5395142589836939": [{"hits_count <= -0.7255547604356459": ["ess", "non_ess"]}, "non_ess"]}, "ess"]}]}, {"NI_ratio <= 0.2513736263736263": ["ess", {"NI <= 0.21236963666719072": ["ess", {"HFI_ratio <= 0.0011723576322587893": [{"insertion_index <= 0.019485580670303967": [{"reads_count <= -0.18959913616018914": ["ess", {"NI <= 0.4764665374821837": [{"NI <= 0.39056949181405776": [{"HFI_normalized <= 0.16792738275340394": [{"insertion_index <= 0.016641452344931914": ["ess", {"insertion_index <= 0.017135325131810198": ["non_ess", "ess"]}]}, {"NI_ratio <= 0.31687242798353904": [{"NI_ratio <= 0.2551229508196721": ["non_ess", "ess"]}, {"orf_len <= -0.3404696225843257": ["ess", "non_ess"]}]}]}, "ess"]}, "non_ess"]}]}, "ess"]}, {"NI_ratio <= 0.3787878787878788": [{"reads_count <= -0.19568829059635653": ["non_ess", "ess"]}, "non_ess"]}]}]}]}]}, "ess"]}, {"HFI_ratio <= 0.000251846571795366": [{"NI <= 0.546855365474339": [{"insertion_index <= 0.01394523326572008": [{"orf_len <= 2.3670827602180378": ["ess", "non_ess"]}, "non_ess"]}, "ess"]}, {"NI_ratio <= 0.2597560302478336": ["ess", {"insertion_index <= 0.016846361185983826": ["ess", {"HFI_ratio <= 0.00031134686346863464": ["ess", "non_ess"]}]}]}]}]}]}, {"NI_ratio <= 0.0": [{"orf_len <= -0.940330170637216": ["ess", {"orf_len <= -0.9321502540728585": ["non_ess", "ess"]}]}, {"HFI_ratio <= 0.002531645569620253": [{"insertion_index <= 0.0152990264255911": ["non_ess", "ess"]}, "non_ess"]}]}]}]}, {"HFI_ratio <= 0.00043857876227818417": [{"NI <= 0.30082334549244394": [{"HFI_ratio <= 7.064981582303124e-05": ["ess", {"insertion_index <= 0.007920792079207921": [{"hits_count <= -0.9996570855415712": ["non_ess", "ess"]}, {"insertion_index <= 0.014948256036795709": [{"hits_count <= 0.2794870982860795": [{"HFI_ratio <= 0.0001413771325580712": ["ess", {"HFI_normalized <= 0.14375": ["ess", {"hits_count <= -0.4514524353297208": ["ess", "non_ess"]}]}]}, "non_ess"]}, {"HFI_ratio <= 0.0002453601761560239": ["non_ess", "ess"]}]}]}]}, {"orf_len <= 0.20213150951806144": [{"hits_count <= -0.26871755192577074": ["non_ess", "ess"]}, {"hits_count <= 0.14243593573311691": [{"HFI_normalized <= 0.125987525987526": ["ess", "non_ess"]}, "non_ess"]}]}]}, {"NI <= 0.5929071473485642": [{"NI <= 0.09098811938568532": [{"HFI_ratio <= 0.001444975831820158": ["ess", {"reads_count <= -0.2368362129983363": ["non_ess", "ess"]}]}, {"insertion_index <= 0.028181818181818183": [{"orf_len <= -0.013272960010021907": [{"orf_len <= -0.01872623771959364": [{"reads_count <= -0.18535518003801185": [{"NI_ratio <= 0.6790123456790124": [{"orf_len <= -0.8121781444622804": [{"HFI_normalized <= 0.2493765586034913": ["ess", "non_ess"]}, "ess"]}, {"reads_count <= -0.18830749734039606": [{"hits_count <= -0.9539733646905836": [{"orf_len <= -0.7521920896569914": [{"HFI_ratio <= 0.0019632186692506463": ["ess", {"HFI_normalized <= 0.4298507462686567": ["ess", "non_ess"]}]}, "non_ess"]}, "non_ess"]}, "ess"]}]}, "non_ess"]}, "ess"]}, "non_ess"]}, "ess"]}]}, "non_ess"]}]}]}, {"HFI_normalized <= 0.18973214285714285": [{"NI_ratio <= 0.3820224719101124": [{"insertion_index <= 0.015850144092219017": ["ess", {"NI_ratio <= 0.2211050598147372": [{"HFI_normalized <= 0.16958174904942966": ["ess", "non_ess"]}, {"hits_count <= -0.08598266852182067": ["non_ess", {"HFI_ratio <= 0.00017173921252809646": ["non_ess", {"ratio_hits_prom <= 0.875": ["non_ess", {"NI <= 0.27007963429370063": ["non_ess", "ess"]}]}]}]}]}]}, "non_ess"]}, {"HFI_normalized <= 0.1911468812877264": ["ess", {"hits_count_pro <= 2": [{"orf_len <= 0.24030445348506355": [{"NI_ratio <= 0.35806451612903223": [{"hits_count <= -0.9996570855415712": ["non_ess", {"ratio_hits_prom <= 1.8000000000000005": [{"reads_count <= -0.2340684155273511": ["ess", {"orf_len <= 0.03853317823090953": [{"hits_count <= -0.8169222021376209": ["non_ess", {"reads_count <= -0.1967954095847506": ["ess", {"reads_count <= -0.08128599512896902": ["non_ess", "ess"]}]}]}, "ess"]}]}, {"NI_ratio <= 0.1905612244897959": ["non_ess", "ess"]}]}]}, {"ratio_hits_prom <= 1.222222222222222": ["non_ess", {"HFI_normalized <= 0.19545454545454544": ["ess", {"orf_len <= 0.2212179815015625": [{"HFI_normalized <= 0.5145772594752187": [{"hits_count <= -0.9996570855415712": [{"HFI_ratio <= 0.0007357701339436084": ["non_ess", "ess"]}, "non_ess"]}, {"ratio_hits_prom <= 1.3333333333333333": ["ess", {"ratio_hits_prom <= 2.5": ["non_ess", "ess"]}]}]}, "ess"]}]}]}]}, "non_ess"]}, {"hits_count <= -0.26871755192577074": [{"insertion_index <= 0.0": ["ess", {"ratio_hits_prom <= 5.333333333333333": ["non_ess", "ess"]}]}, {"NI_ratio <= 0.512937062937063": [{"ratio_hits_prom <= 1.0833333333333333": ["non_ess", "ess"]}, {"HFI_normalized <= 0.2192159028161237": [{"hits_count_pro <= 6": ["non_ess", "ess"]}, "non_ess"]}]}]}]}]}]}]}, {"NI_ratio <= 0.4703557312252964": [{"NI_ratio <= 0.3318452380952381": [{"HFI_ratio <= 0.0012807728549341776": [{"hits_count_pro <= 0": [{"hits_count <= -0.9996570855415712": [{"orf_len <= -0.7203813030178229": ["ess", {"NI <= 0.09313077192625498": ["non_ess", "ess"]}]}, {"insertion_index <= 0.028433734939759037": [{"reads_count <= -0.21967586867822814": ["ess", {"NI <= 0.34658399717458704": [{"NI_ratio <= 0.1887096774193548": [{"orf_len <= -0.32956306716518224": [{"HFI_normalized <= 0.31357254290171604": [{"reads_count <= -0.21081891677107556": ["non_ess", "ess"]}, "non_ess"]}, {"insertion_index <= 0.011007911936704506": [{"NI_ratio <= 0.11874999999999998": [{"HFI_ratio <= 0.0006654002597207466": ["ess", "non_ess"]}, "non_ess"]}, "ess"]}]}, {"orf_len <= -0.0659879778692153": [{"reads_count <= -0.15121901122919462": ["ess", "non_ess"]}, "ess"]}]}, {"HFI_normalized <= 0.11184439041333796": ["non_ess", {"insertion_index <= 0.026850507982583455": [{"reads_count <= -0.12944567112411118": [{"hits_count <= -0.1773501102237957": [{"NI <= 0.6744821497294727": ["ess", "non_ess"]}, {"insertion_index <= 0.014345487148834431": ["ess", "non_ess"]}]}, "ess"]}, "non_ess"]}]}]}]}, "ess"]}]}, {"ratio_hits_prom <= 2.8000000000000003": [{"HFI_normalized <= 0.100418410041841": ["ess", {"ratio_hits_prom <= 1.0434782608695652": [{"NI_ratio <= 0.1981796829125073": [{"NI <= 0.243978091442706": ["non_ess", "ess"]}, "non_ess"]}, {"HFI_normalized <= 0.16540130151843818": [{"NI <= 0.4634633855610996": ["non_ess", {"ratio_hits_prom <= 1.2666666666666668": ["ess", "non_ess"]}]}, {"reads_count <= -0.22576502311439556": ["non_ess", {"HFI_ratio <= 0.0007710949548358669": [{"insertion_index <= 0.01174496644295302": [{"hits_count <= -0.26871755192577074": ["ess", {"reads_count <= -0.11431504494939218": ["non_ess", "ess"]}]}, "ess"]}, {"reads_count <= -0.21100343660247456": ["ess", "non_ess"]}]}]}]}]}]}, "ess"]}]}, {"orf_len <= -0.6513064520299143": [{"orf_len <= -0.8012715890431369": [{"reads_count <= -0.2377588121553313": [{"HFI_ratio <= 0.0027397260273972607": [{"HFI_ratio <= 0.0024877140502426666": ["non_ess", "ess"]}, "non_ess"]}, {"NI <= 0.8235681369321922": [{"reads_count <= -0.2351755345157452": [{"HFI_normalized <= 0.7789203084832905": ["ess", "non_ess"]}, {"insertion_index <= 0.025477707006369428": ["non_ess", {"insertion_index <= 0.032085561497326213": ["ess", "non_ess"]}]}]}, "non_ess"]}]}, {"HFI_normalized <= 0.349609375": ["non_ess", "ess"]}]}, "non_ess"]}]}, {"ratio_hits_prom <= 0.0": [{"hits_count <= -0.8169222021376209": ["non_ess", {"HFI_ratio <= 0.0011507479861910242": [{"insertion_index <= 0.010689470871191877": ["ess", {"HFI_ratio <= 0.0007693024990675122": [{"reads_count <= -0.17243879184008098": [{"hits_count <= -0.2230338310747832": [{"NI_ratio <= 0.4576719576719576": ["non_ess", "ess"]}, "non_ess"]}, {"orf_len <= -0.1632380970232445": ["ess", {"HFI_ratio <= 0.00036228829611385777": [{"HFI_normalized <= 0.11569813305285301": ["ess", {"insertion_index <= 0.016538037486218304": [{"HFI_ratio <= 0.0001520766522392411": [{"HFI_normalized <= 0.1219284603421462": ["ess", "non_ess"]}, "ess"]}, "non_ess"]}]}, "non_ess"]}]}]}, "ess"]}]}, "non_ess"]}]}, {"NI_ratio <= 0.4675324675324675": [{"HFI_ratio <= 0.00037102145740762005": [{"NI <= 0.20254951058502169": ["ess", {"orf_len <= 2.8387912820959933": ["non_ess", "ess"]}]}, "non_ess"]}, "ess"]}]}]}, {"insertion_index <= 0.02182428651371013": [{"hits_count_pro <= 0": [{"NI <= 0.1631020848310568": [{"NI_ratio <= 0.8186274509803921": [{"HFI_normalized <= 0.6758793969849246": [{"orf_len <= 0.9546838334389602": ["non_ess", "ess"]}, "ess"]}, {"orf_len <= -0.8803441158319271": ["ess", {"NI <= 0.0927132079075542": [{"NI <= 0.03180489608244088": ["non_ess", "ess"]}, "non_ess"]}]}]}, {"insertion_index <= 0.0199501246882793": [{"NI_ratio <= 0.5377225866916588": [{"NI <= 0.20383672024755595": ["non_ess", {"HFI_ratio <= 3.838054604383733e-05": ["non_ess", "ess"]}]}, {"insertion_index <= 0.01991150442477876": [{"HFI_ratio <= 0.0007130760317318834": [{"orf_len <= -0.22322415182853356": [{"HFI_ratio <= 0.0005776619468551009": [{"orf_len <= -0.2777569289242508": ["non_ess", "ess"]}, "ess"]}, {"NI_ratio <= 0.8788551690106093": [{"hits_count <= 0.41653826083904205": [{"HFI_ratio <= 0.00034694705916462113": [{"NI_ratio <= 0.5954861111111112": ["non_ess", "ess"]}, "non_ess"]}, {"NI <= 0.4852397429560059": ["non_ess", "ess"]}]}, "non_ess"]}]}, {"orf_len <= -0.940330170637216": ["ess", {"NI_ratio <= 0.7612903225806452": [{"orf_len <= -0.5231544258549787": [{"NI_ratio <= 0.7198515769944341": ["non_ess", "ess"]}, "non_ess"]}, "non_ess"]}]}]}, "ess"]}]}, "non_ess"]}]}, {"insertion_index <= 0.021739130434782608": [{"hits_count_pro <= 2": [{"NI <= 0.43688271312392185": [{"ratio_hits_prom <= 1.2777777777777777": [{"insertion_index <= 0.008674698795180723": [{"HFI_normalized <= 0.3436144578313253": ["ess", "non_ess"]}, "non_ess"]}, {"ratio_hits_prom <= 1.35": [{"insertion_index <= 0.013022410660205937": ["non_ess", "ess"]}, {"orf_len <= -0.9239703375085008": [{"orf_len <= -0.939421291018954": ["non_ess", "ess"]}, {"reads_count <= -0.1508499715663966": ["non_ess", {"NI <= 0.3869261703670605": [{"hits_count <= -0.36008499362774576": [{"insertion_index <= 0.007805724197745012": ["ess", "non_ess"]}, "non_ess"]}, "ess"]}]}]}]}]}, "non_ess"]}, "non_ess"]}, "ess"]}]}, {"NI_ratio <= 0.6669230769230771": [{"hits_count_pro <= 0": [{"NI <= 0.4818816736366145": [{"insertion_index <= 0.02690582959641256": ["non_ess", "ess"]}, "non_ess"]}, "non_ess"]}, "non_ess"]}]}]}, {"NI_ratio <= 0.5264830508474576": [{"HFI_ratio <= 0.0006901480147231576": [{"NI_ratio <= 0.33356741573033705": [{"insertion_index <= 0.03195266272189349": [{"HFI_ratio <= 0.000618134736666249": [{"hits_count_pro <= 2": [{"HFI_ratio <= 0.00036344977979219225": [{"orf_len <= -0.4413552602114028": ["non_ess", {"NI_ratio <= 0.0824074074074074": [{"hits_count <= -0.9996570855415712": ["non_ess", "ess"]}, {"NI_ratio <= 0.21236432279377065": [{"HFI_ratio <= 9.474039450124508e-05": ["non_ess", {"NI <= 0.1996021289227276": ["ess", {"NI <= 0.2826198461234958": [{"HFI_ratio <= 0.0002543228575034709": ["non_ess", {"insertion_index <= 0.011304757418747056": ["ess", "non_ess"]}]}, {"reads_count <= -0.0995534584374712": ["ess", {"hits_count <= 0.8733754693489172": ["non_ess", "ess"]}]}]}]}]}, {"NI_ratio <= 0.2532408803135363": ["ess", {"hits_count <= 1.4672638404117548": [{"reads_count <= -0.1314753892695003": [{"NI_ratio <= 0.2913988368533823": [{"HFI_ratio <= 0.000209775540172016": ["ess", "non_ess"]}, "non_ess"]}, {"NI_ratio <= 0.26418242491657395": ["non_ess", "ess"]}]}, "non_ess"]}]}]}]}]}, {"HFI_ratio <= 0.0005433163901535362": ["ess", {"orf_len <= -0.2713947715964171": ["non_ess", "ess"]}]}]}, {"HFI_normalized <= 0.12095933263816475": [{"orf_len <= 0.12305898272927135": ["ess", "non_ess"]}, {"HFI_normalized <= 0.19366715758468336": ["non_ess", "ess"]}]}]}, "ess"]}, "ess"]}, {"insertion_index <= 0.01501305483028721": [{"hits_count_pro <= 1": [{"NI_ratio <= 0.3536399302528335": ["non_ess", {"HFI_normalized <= 0.13402061855670105": ["ess", {"NI_ratio <= 0.3764880952380952": ["ess", {"insertion_index <= 0.0140218878248974": [{"reads_count <= -0.08755966939653542": [{"reads_count <= -0.19753348891034667": ["non_ess", {"HFI_normalized <= 0.22333077513430544": [{"NI_ratio <= 0.3989586265128061": ["ess", "non_ess"]}, {"hits_count <= -0.9082896438395959": ["non_ess", "ess"]}]}]}, "non_ess"]}, "ess"]}]}]}]}, {"ratio_hits_prom <= 2.2": ["non_ess", "ess"]}]}, {"hits_count_pro <= 0": [{"NI <= 0.6071602615135944": [{"NI_ratio <= 0.4141182466870541": ["ess", {"reads_count <= -0.058774575698289526": ["non_ess", "ess"]}]}, "ess"]}, "non_ess"]}]}]}, {"ratio_hits_prom <= 0.6981132075471698": [{"NI <= 0.07181953664815066": ["non_ess", {"hits_count <= 0.32517081913706697": [{"HFI_ratio <= 0.0008057708541171053": [{"reads_count <= -0.17963506526464249": ["non_ess", "ess"]}, {"NI_ratio <= 0.2513736263736263": [{"HFI_normalized <= 0.20823244552058112": ["non_ess", {"NI_ratio <= 0.18406593406593405": [{"NI <= 0.23467952287447616": ["ess", {"insertion_index <= 0.01171875": ["non_ess", {"NI_ratio <= 0.09860248447204968": ["ess", "non_ess"]}]}]}, "ess"]}]}, {"NI_ratio <= 0.3321604503870513": ["non_ess", {"NI_ratio <= 0.3652058432934927": ["ess", {"NI <= 0.6792753748808182": [{"HFI_ratio <= 0.0017564326916844901": ["ess", "non_ess"]}, "non_ess"]}]}]}]}]}, "non_ess"]}]}, {"HFI_normalized <= 0.2058823529411765": [{"HFI_normalized <= 0.18756476683937826": ["non_ess", {"NI <= 0.4433324798788837": ["non_ess", {"reads_count <= 0.07278806408920616": ["ess", "non_ess"]}]}]}, "non_ess"]}]}]}, {"NI_ratio <= 0.6982674076495587": [{"NI_ratio <= 0.6735033259423502": [{"orf_len <= 2.4407020092972567": [{"reads_count <= -0.1299992306183082": [{"HFI_ratio <= 0.0007623200014563727": [{"NI <= 0.4185774539877301": [{"HFI_ratio <= 0.00039392523250152313": [{"HFI_normalized <= 0.09790428526743823": ["ess", "non_ess"]}, "ess"]}, "non_ess"]}, {"HFI_ratio <= 0.002671460067134089": ["non_ess", {"NI <= 0.5800527215318212": [{"insertion_index <= 0.005063291139240506": ["ess", "non_ess"]}, "ess"]}]}]}, {"reads_count <= 0.09548400335128464": ["non_ess", {"reads_count <= 0.09898988014786587": ["ess", "non_ess"]}]}]}, "ess"]}, {"hits_count_pro <= 1": [{"insertion_index <= 0.02119815668202765": ["ess", {"HFI_ratio <= 0.0020337265687196933": ["non_ess", "ess"]}]}, "non_ess"]}]}, {"hits_count_pro <= 0": [{"hits_count <= 0.05106849403114188": [{"HFI_ratio <= 0.002493765586034913": [{"HFI_normalized <= 0.6914893617021277": [{"insertion_index <= 0.011296882060551287": ["non_ess", {"NI <= 0.2832124147907854": [{"orf_len <= -0.2777569289242508": ["non_ess", {"hits_count <= -0.2230338310747832": ["ess", "non_ess"]}]}, {"orf_len <= -0.4331753436470451": [{"insertion_index <= 0.013904982618771726": ["ess", {"hits_count <= 0.005384773180154362": ["non_ess", "ess"]}]}, "non_ess"]}]}]}, {"NI <= 0.14431656536919693": ["non_ess", "ess"]}]}, "non_ess"]}, "non_ess"]}, {"HFI_normalized <= 0.2174236783320924": ["non_ess", {"orf_len <= -0.9594166426207172": [{"reads_count <= -0.15527844751997288": ["non_ess", "ess"]}, {"HFI_normalized <= 0.2192159028161237": ["ess", {"ratio_hits_prom <= 1.9411764705882355": ["non_ess", {"NI <= 0.5222769088051126": ["non_ess", {"hits_count <= -0.7712384812866334": ["ess", "non_ess"]}]}]}]}]}]}]}]}]}]