[{"insertion_index <= 0.0058762530245419975": [{"hits_count_pro <= 0": [{"insertion_index <= 0.003154574132492113": [{"HFI_normalized <= 1309": [{"HFI_normalized <= 1174": [{"HFI_normalized <= 921": [{"HFI_normalized <= 871": [{"orf_len <= -0.7521920896569914": [{"HFI_normalized <= 221": ["ess", {"HFI_normalized <= 362": ["non_ess", {"orf_len <= -0.7603720062213489": [{"reads_count <= -0.4424401359922946": ["ess", "non_ess"]}, "non_ess"]}]}]}, {"reads_count <= -0.38733373142995337": [{"orf_len <= -0.5340609812741222": ["ess", {"orf_len <= -0.4713482876140472": ["non_ess", {"orf_len <= -0.1986844021354608": ["ess", {"NI <= 0.08437906022133909": [{"insertion_index <= 0.002729257641921397": [{"orf_len <= -0.02417951542916537": [{"orf_len <= -0.16051145816845866": ["non_ess", "ess"]}, "ess"]}, "non_ess"]}, "ess"]}]}]}]}, {"hits_count <= -0.6139380912921409": [{"insertion_index <= 0.0010141987829614604": ["ess", "non_ess"]}, "ess"]}]}]}, {"orf_len <= 0.3684564796599992": ["non_ess", "ess"]}]}, "ess"]}, "non_ess"]}, "ess"]}, {"insertion_index <= 0.003218884120171674": ["non_ess", {"reads_count <= -0.3525296864432115": [{"HFI_normalized <= 537": [{"HFI_normalized <= 310": [{"insertion_index <= 0.003838771593090211": ["non_ess", {"NI <= 0.182522251762802": [{"HFI_normalized <= 305": ["ess", "non_ess"]}, "non_ess"]}]}, "ess"]}, {"HFI_normalized <= 662": [{"orf_len <= 0.7638191136039496": ["non_ess", "ess"]}, {"HFI_normalized <= 824": ["ess", "non_ess"]}]}]}, {"HFI_normalized <= 1287": [{"HFI_normalized <= 1094": [{"insertion_index <= 0.003798155181768855": ["non_ess", {"HFI_normalized <= 976": [{"hits_count <= -0.2088908492554616": [{"reads_count <= -0.3206259785386981": [{"HFI_normalized <= 429": ["ess", "non_ess"]}, {"reads_count <= -0.24811755148298595": ["ess", "non_ess"]}]}, {"orf_len <= 2.170764762673456": ["non_ess", {"orf_len <= 2.298916788848392": ["ess", "non_ess"]}]}]}, "ess"]}]}, "non_ess"]}, "ess"]}]}]}]}, {"insertion_index <= 0.0013513513513513516": [{"insertion_index <= 0.0011867088607594935": [{"orf_len <= -0.6294933411916275": ["ess", {"HFI_normalized <= 785": ["non_ess", {"reads_count <= -0.42793845058115215": ["ess", "non_ess"]}]}]}, "ess"]}, {"NI <= 0.1835011488670117": [{"hits_count_pro <= 2": [{"hits_count <= -0.6139380912921409": [{"hits_count <= -0.6718019830116665": [{"insertion_index <= 0.0038572806171648993": [{"NI <= 0.03963527714815578": [{"orf_len <= -0.8339912553005673": ["ess", "non_ess"]}, "non_ess"]}, {"HFI_normalized <= 440": [{"insertion_index <= 0.003861003861003861": ["ess", "non_ess"]}, "ess"]}]}, "ess"]}, "non_ess"]}, "non_ess"]}, {"NI <= 0.19643055055276945": [{"orf_len <= 1.7644955733103622": ["ess", "non_ess"]}, {"HFI_normalized <= 263": [{"HFI_normalized <= 148": ["non_ess", "ess"]}, {"HFI_normalized <= 956": ["non_ess", "ess"]}]}]}]}]}]}, {"hits_count <= 0.022564717622640867": [{"hits_count_pro <= 0": [{"orf_len <= -0.8476244495744967": ["non_ess", {"reads_count <= -0.33512766394984056": [{"reads_count <= -0.3467290122787545": [{"insertion_index <= 0.010706638115631693": [{"HFI_normalized <= 340": [{"hits_count <= -0.6718019830116665": ["non_ess", {"insertion_index <= 0.005917159763313609": ["non_ess", "ess"]}]}, "non_ess"]}, "non_ess"]}, "ess"]}, {"HFI_normalized <= 245": ["non_ess", {"reads_count <= -0.05959564113813427": [{"NI <= 0.10993811561324413": ["ess", {"reads_count <= -0.2539182256474429": [{"HFI_normalized <= 383": [{"HFI_normalized <= 301": [{"HFI_normalized <= 246": ["ess", "non_ess"]}, "ess"]}, "non_ess"]}, "non_ess"]}]}, {"HFI_normalized <= 796": ["ess", "non_ess"]}]}]}]}]}, {"insertion_index <= 0.04105571847507331": [{"HFI_normalized <= 817": [{"insertion_index <= 0.008958566629339306": ["non_ess", {"NI <= 0.27869085954917017": [{"orf_len <= -0.4113622328087582": [{"HFI_normalized <= 260": [{"hits_count_pro <= 10": ["non_ess", "ess"]}, {"hits_count_pro <= 2": ["ess", "non_ess"]}]}, "non_ess"]}, {"hits_count_pro <= 3": [{"reads_count <= -0.3525296864432115": [{"NI <= 0.4315720328120995": ["non_ess", {"NI <= 0.4971518987341772": ["ess", "non_ess"]}]}, {"orf_len <= -0.2968434009077519": ["non_ess", {"hits_count_pro <= 2": ["non_ess", "ess"]}]}]}, "non_ess"]}]}]}, "ess"]}, {"insertion_index <= 0.0410958904109589": ["ess", "non_ess"]}]}]}, {"reads_count <= 3.8500587457058666": ["non_ess", {"reads_count <= 4.2358035776422565": ["ess", "non_ess"]}]}]}]}, {"insertion_index <= 0.005813953488372093": [{"hits_count_pro <= 0": [{"orf_len <= -0.8503510884292825": [{"insertion_index <= 0.0031847133757961785": [{"HFI_normalized <= 362": ["non_ess", "ess"]}, "ess"]}, {"hits_count <= -0.2088908492554616": [{"orf_len <= 1.4245745960803908": [{"HFI_normalized <= 877": [{"HFI_normalized <= 838": [{"orf_len <= 1.0773825819043241": [{"hits_count <= -0.3824825244140385": [{"orf_len <= 0.9901301385511764": [{"HFI_normalized <= 642": [{"orf_len <= 0.6520269205577292": [{"HFI_normalized <= 562": [{"HFI_normalized <= 525": [{"HFI_normalized <= 519": [{"NI <= 0.15647240845796806": [{"orf_len <= 0.5702277549141532": ["ess", "non_ess"]}, {"HFI_normalized <= 310": ["non_ess", "ess"]}]}, "non_ess"]}, "ess"]}, {"orf_len <= -0.4304487047922593": ["non_ess", {"reads_count <= -0.4105364280877813": ["ess", "non_ess"]}]}]}, "non_ess"]}, {"HFI_normalized <= 790": [{"orf_len <= 0.4475290064487893": ["ess", {"reads_count <= -0.3931344055944103": ["non_ess", "ess"]}]}, {"HFI_normalized <= 821": ["non_ess", "ess"]}]}]}, "non_ess"]}, "ess"]}, {"reads_count <= -0.2655195739763569": ["non_ess", "ess"]}]}, {"NI <= 0.039507290035661335": ["ess", "non_ess"]}]}, {"HFI_normalized <= 1095": ["ess", {"orf_len <= 0.033079900521337795": ["non_ess", {"insertion_index <= 0.0035323207347227135": [{"orf_len <= 0.8510715569570974": ["ess", {"reads_count <= -0.3931344055944103": ["non_ess", "ess"]}]}, "non_ess"]}]}]}]}, "ess"]}, {"HFI_normalized <= 648": ["non_ess", {"hits_count <= 0.022564717622640867": [{"insertion_index <= 0.005639760310186817": [{"reads_count <= -0.2800212593874993": ["non_ess", "ess"]}, "non_ess"]}, {"HFI_normalized <= 728": ["ess", "non_ess"]}]}]}]}]}, {"insertion_index <= 0.002631578947368421": [{"orf_len <= 0.027626622811766068": [{"reads_count <= -0.4540414843212086": [{"insertion_index <= 0.0012531328320802006": [{"reads_count <= -0.45694182140343703": [{"orf_len <= -0.7140191456899893": [{"HFI_normalized <= 239": ["ess", "non_ess"]}, "ess"]}, "non_ess"]}, "ess"]}, "non_ess"]}, {"hits_count_pro <= 3": ["ess", "non_ess"]}]}, {"insertion_index <= 0.005226480836236934": [{"HFI_normalized <= 402": ["non_ess", {"HFI_normalized <= 411": ["ess", {"hits_count_pro <= 4": [{"hits_count <= -0.6718019830116665": [{"reads_count <= -0.4395397989100661": ["non_ess", "ess"]}, {"orf_len <= 0.6056740600263695": ["non_ess", {"hits_count <= -0.3824825244140385": ["ess", {"NI <= 0.1341332589802602": ["ess", "non_ess"]}]}]}]}, "non_ess"]}]}]}, {"NI <= 0.19242239677405806": ["non_ess", {"hits_count_pro <= 2": ["ess", "non_ess"]}]}]}]}]}, {"insertion_index <= 0.010471204188481676": [{"hits_count_pro <= 0": [{"orf_len <= 1.0528428322112513": [{"HFI_normalized <= 314": [{"reads_count <= -0.33512766394984056": [{"orf_len <= -0.6949326737064881": [{"orf_len <= -0.940330170637216": [{"insertion_index <= 0.006896551724137931": ["non_ess", "ess"]}, "non_ess"]}, {"orf_len <= -0.5231544258549787": ["ess", {"reads_count <= -0.3757323831010394": ["non_ess", "ess"]}]}]}, "non_ess"]}, {"NI <= 0.2389351690803567": [{"orf_len <= -0.8530777272840684": ["non_ess", {"HFI_normalized <= 1292": [{"orf_len <= -0.1386983473301717": ["ess", {"orf_len <= 0.013993428537836741": ["non_ess", {"orf_len <= 0.2075847872276332": ["ess", {"insertion_index <= 0.008092485549132947": [{"orf_len <= 0.3248302579834253": ["non_ess", "ess"]}, "non_ess"]}]}]}]}, "non_ess"]}]}, {"HFI_normalized <= 504": [{"HFI_normalized <= 320": ["ess", "non_ess"]}, {"orf_len <= 0.938324000310245": [{"orf_len <= -0.33228970601996816": ["ess", "non_ess"]}, "ess"]}]}]}]}, "non_ess"]}, {"HFI_normalized <= 1015": [{"NI <= 0.18273034803050284": [{"orf_len <= -0.9212436986537148": ["ess", "non_ess"]}, "non_ess"]}, {"orf_len <= 1.0283030825181785": ["ess", "non_ess"]}]}]}, {"reads_count <= -0.33802800103206904": [{"hits_count_pro <= 1": [{"orf_len <= -0.8776174769771412": ["non_ess", {"hits_count <= -0.32461863269451285": [{"orf_len <= -0.6622130074490578": ["non_ess", "ess"]}, "non_ess"]}]}, "non_ess"]}, "non_ess"]}]}]}, {"insertion_index <= 0.00585480093676815": [{"NI <= 0.054041806267616906": [{"reads_count <= -0.38733373142995337": [{"reads_count <= -0.4076360910055528": [{"NI <= 0.027543201536054617": [{"NI <= 0.02199725432080807": [{"HFI_normalized <= 512": [{"hits_count_pro <= 0": [{"orf_len <= -0.8830707546867129": ["ess", {"orf_len <= -0.7521920896569914": [{"orf_len <= -0.8639842827032118": ["ess", "non_ess"]}, {"orf_len <= -0.3977290385348289": ["ess", "non_ess"]}]}]}, "non_ess"]}, {"orf_len <= -0.3513761780034692": [{"HFI_normalized <= 791": ["ess", "non_ess"]}, "ess"]}]}, {"insertion_index <= 0.0007251631617113853": ["ess", "non_ess"]}]}, {"orf_len <= -0.4413552602114028": [{"orf_len <= -0.5449675366932656": ["ess", "non_ess"]}, "ess"]}]}, {"insertion_index <= 0.0016590626296142678": ["non_ess", "ess"]}]}, "ess"]}, {"orf_len <= 0.019446706247408473": [{"hits_count_pro <= 2": [{"orf_len <= -0.9076105043797856": ["non_ess", {"HFI_normalized <= 680": [{"NI <= 0.07786374186501616": [{"orf_len <= -0.7740052004952783": [{"HFI_normalized <= 249": ["ess", "non_ess"]}, "ess"]}, {"orf_len <= -0.3895491219704713": [{"orf_len <= -0.4931613984523342": [{"NI <= 0.13293368302735106": ["non_ess", {"NI <= 0.15647240845796806": ["ess", {"reads_count <= -0.4250381134989237": [{"orf_len <= -0.8312646164457814": ["non_ess", "ess"]}, "non_ess"]}]}]}, {"reads_count <= -0.43083878766338063": ["non_ess", "ess"]}]}, {"orf_len <= -0.14142498618495758": [{"orf_len <= -0.3241097894556105": [{"HFI_normalized <= 421": ["non_ess", "ess"]}, "non_ess"]}, {"NI <= 0.1276522190052288": ["ess", "non_ess"]}]}]}]}, "non_ess"]}]}, "non_ess"]}, {"hits_count <= -0.4403464161335641": [{"hits_count_pro <= 0": [{"insertion_index <= 0.0019096117122851689": ["non_ess", {"reads_count <= -0.33802800103206904": [{"NI <= 0.08437906022133909": [{"insertion_index <= 0.0029254022428083864": [{"orf_len <= 0.6465736428481574": ["non_ess", "ess"]}, "ess"]}, "ess"]}, {"insertion_index <= 0.004542504866969501": [{"NI <= 0.07212314664516903": ["non_ess", "ess"]}, "non_ess"]}]}]}, {"orf_len <= 0.4093560624817872": [{"hits_count <= -0.5560741995726153": [{"NI <= 0.08399081839500774": [{"reads_count <= -0.4221377764166952": ["ess", "non_ess"]}, "ess"]}, "non_ess"]}, "non_ess"]}]}, {"hits_count_pro <= 2": [{"HFI_normalized <= 1287": [{"insertion_index <= 0.005458956732713303": [{"insertion_index <= 0.004187285877426722": [{"NI <= 0.15386037910309755": [{"NI <= 0.12613066045154925": [{"reads_count <= -0.2945229447986418": ["ess", "non_ess"]}, "ess"]}, "non_ess"]}, {"orf_len <= 0.7147396142178041": [{"HFI_normalized <= 394": ["non_ess", "ess"]}, "non_ess"]}]}, {"insertion_index <= 0.005639760310186817": ["ess", {"orf_len <= 0.9710436665676754": ["non_ess", "ess"]}]}]}, {"reads_count <= -0.1959114840028732": ["ess", "non_ess"]}]}, "non_ess"]}]}]}]}, {"hits_count_pro <= 2": [{"hits_count <= 0.1382925010616921": [{"insertion_index <= 0.0069124423963133645": [{"insertion_index <= 0.006880733944954129": [{"HFI_normalized <= 201": ["non_ess", {"reads_count <= -0.4105364280877813": [{"reads_count <= -0.42793845058115215": ["non_ess", "ess"]}, {"orf_len <= 0.13669217700320066": ["non_ess", {"hits_count <= -0.2667547409749872": ["ess", {"HFI_normalized <= 505": ["non_ess", "ess"]}]}]}]}]}, "ess"]}, {"reads_count <= -0.3525296864432115": [{"HFI_normalized <= 137": ["non_ess", {"HFI_normalized <= 142": ["ess", {"hits_count_pro <= 0": [{"NI <= 0.28442262981141825": [{"hits_count <= -0.5560741995726153": ["non_ess", "ess"]}, {"reads_count <= -0.36413103477212544": ["ess", "non_ess"]}]}, {"hits_count <= -0.6718019830116665": ["ess", "non_ess"]}]}]}]}, {"HFI_normalized <= 66": ["ess", {"insertion_index <= 0.0169971671388102": [{"insertion_index <= 0.01694915254237288": [{"HFI_normalized <= 243": ["non_ess", {"insertion_index <= 0.011398963730569948": [{"reads_count <= -0.1814097985917308": ["non_ess", {"reads_count <= -0.1698084502628168": ["ess", {"HFI_normalized <= 565": ["non_ess", {"HFI_normalized <= 596": ["ess", "non_ess"]}]}]}]}, {"hits_count <= -0.15102695753593598": [{"HFI_normalized <= 246": ["ess", "non_ess"]}, {"hits_count_pro <= 1": [{"reads_count <= -0.1002003602893331": ["ess", "non_ess"]}, "non_ess"]}]}]}]}, "ess"]}, "non_ess"]}]}]}]}, {"reads_count <= 2.533305710374133": ["non_ess", "ess"]}]}, {"hits_count <= -0.2088908492554616": [{"reads_count <= -0.12630339402938948": ["non_ess", {"hits_count <= -0.5560741995726153": ["non_ess", "ess"]}]}, "non_ess"]}]}]}, {"NI <= 0.1984245262933788": [{"hits_count_pro <= 0": [{"reads_count <= -0.2800212593874993": [{"orf_len <= -0.9157904209441432": [{"orf_len <= -0.940330170637216": [{"orf_len <= -1.0084961420068628": [{"HFI_normalized <= 112": ["ess", "non_ess"]}, "ess"]}, "non_ess"]}, {"NI <= 0.19479580020302392": [{"orf_len <= -0.8176314221718521": ["ess", {"orf_len <= -0.3313808264017062": [{"orf_len <= -0.5395142589836939": [{"orf_len <= -0.7440121730926338": [{"NI <= 0.06667717528373268": ["non_ess", "ess"]}, {"reads_count <= -0.3815330572654964": [{"orf_len <= -0.6158601469176981": ["ess", {"orf_len <= -0.5804138418054818": ["non_ess", "ess"]}]}, "non_ess"]}]}, {"insertion_index <= 0.0010395010395010396": ["ess", {"reads_count <= -0.3235263156209266": [{"reads_count <= -0.4395397989100661": [{"NI <= 0.05264227642276423": ["non_ess", "ess"]}, "non_ess"]}, "ess"]}]}]}, {"HFI_normalized <= 1638": [{"orf_len <= 0.7392793639108769": [{"NI <= 0.043369863822999434": [{"NI <= 0.039302177298811525": [{"orf_len <= 0.033079900521337795": [{"HFI_normalized <= 700": ["ess", {"orf_len <= -0.10597868107274132": [{"orf_len <= -0.18505120786153145": [{"orf_len <= -0.3213831506008247": ["ess", {"HFI_normalized <= 751": ["ess", "non_ess"]}]}, "ess"]}, "non_ess"]}]}, "ess"]}, "non_ess"]}, {"orf_len <= -0.05689918168659575": ["ess", {"insertion_index <= 0.005898123324396783": [{"hits_count <= -0.4982103078530897": [{"insertion_index <= 0.0032537960954446853": [{"reads_count <= -0.3844333943477248": ["ess", {"hits_count <= -0.7296658747311922": ["non_ess", "ess"]}]}, {"HFI_normalized <= 425": ["ess", {"reads_count <= -0.4047357539233243": ["non_ess", "ess"]}]}]}, "ess"]}, {"reads_count <= -0.3322273268676121": ["non_ess", "ess"]}]}]}]}, {"insertion_index <= 0.001243008079552517": ["ess", {"reads_count <= -0.43083878766338063": ["ess", {"reads_count <= -0.3815330572654964": ["non_ess", {"insertion_index <= 0.00370522848909016": [{"orf_len <= 0.8892445009240995": [{"insertion_index <= 0.0021570319240724768": ["non_ess", {"reads_count <= -0.34382867519652605": ["ess", "non_ess"]}]}, "ess"]}, "non_ess"]}]}]}]}]}, "ess"]}]}]}, "non_ess"]}]}, {"HFI_normalized <= 424": ["non_ess", {"orf_len <= 0.1748651209702028": ["ess", {"reads_count <= 0.2623417749892278": [{"reads_count <= -0.1640077760983598": [{"reads_count <= -0.2423168773185289": ["non_ess", {"NI <= 0.1727743957567356": ["ess", "non_ess"]}]}, "non_ess"]}, "ess"]}]}]}]}, {"insertion_index <= 0.000846740050804403": [{"HFI_normalized <= 461": [{"HFI_normalized <= 244": ["ess", "non_ess"]}, "ess"]}, {"NI <= 0.18248372591812165": [{"insertion_index <= 0.004207573632538568": [{"reads_count <= -0.16690811318058832": [{"insertion_index <= 0.0039929015084294575": [{"HFI_normalized <= 249": [{"orf_len <= -0.8857973935414988": ["non_ess", "ess"]}, {"orf_len <= 0.0957925941814127": ["non_ess", {"reads_count <= -0.4105364280877813": ["ess", {"HFI_normalized <= 1118": ["non_ess", {"reads_count <= -0.36413103477212544": ["ess", "non_ess"]}]}]}]}]}, "ess"]}, "ess"]}, {"hits_count <= -0.2667547409749872": ["non_ess", {"reads_count <= -0.2945229447986418": ["ess", {"orf_len <= 0.12305898272927135": ["ess", "non_ess"]}]}]}]}, {"reads_count <= -0.3699317089365824": ["ess", {"hits_count_pro <= 1": [{"NI <= 0.1930526968731497": [{"HFI_normalized <= 1065": ["non_ess", "ess"]}, "ess"]}, "non_ess"]}]}]}]}]}, {"hits_count_pro <= 0": [{"insertion_index <= 0.010795681727309077": [{"reads_count <= -0.4105364280877813": [{"orf_len <= -0.9430568094920021": ["non_ess", {"HFI_normalized <= 152": [{"reads_count <= -0.4424401359922946": ["ess", "non_ess"]}, "ess"]}]}, {"HFI_normalized <= 782": [{"hits_count <= -0.15102695753593598": [{"reads_count <= -0.2655195739763569": [{"NI <= 0.2837995144178003": ["non_ess", {"HFI_normalized <= 379": [{"reads_count <= -0.33512766394984056": ["ess", "non_ess"]}, "non_ess"]}]}, {"reads_count <= -0.14370541652276042": [{"reads_count <= -0.2104131694140156": [{"NI <= 0.2147093285984508": ["non_ess", "ess"]}, "non_ess"]}, "ess"]}]}, {"NI <= 0.205613247073112": ["ess", "non_ess"]}]}, {"HFI_normalized <= 1095": [{"reads_count <= -0.34382867519652605": ["non_ess", "ess"]}, "non_ess"]}]}]}, {"HFI_normalized <= 309": ["non_ess", {"orf_len <= -0.05689918168659575": [{"reads_count <= -0.29162260771641324": ["non_ess", {"orf_len <= -0.4113622328087582": ["ess", {"HFI_normalized <= 418": ["non_ess", "ess"]}]}]}, "non_ess"]}]}]}, {"hits_count <= 0.1382925010616921": [{"NI <= 0.40564678345463184": [{"orf_len <= -0.34592290029389744": [{"orf_len <= -0.4386286213566168": [{"orf_len <= -0.962143281475503": [{"orf_len <= -0.9921363088781476": ["non_ess", "ess"]}, {"NI <= 0.4023914572543002": [{"hits_count_pro <= 10": ["non_ess", {"HFI_normalized <= 102": ["non_ess", "ess"]}]}, "ess"]}]}, {"reads_count <= -0.3409283381142976": ["ess", {"orf_len <= -0.4304487047922593": ["ess", {"hits_count_pro <= 9": ["non_ess", "ess"]}]}]}]}, {"NI <= 0.3942605126948639": [{"orf_len <= 1.5927173254588527": ["non_ess", "ess"]}, "ess"]}]}, {"insertion_index <= 0.04105571847507331": ["non_ess", {"NI <= 1.1361233955344618": ["ess", "non_ess"]}]}]}, "non_ess"]}]}]}, {"insertion_index <= 0.005898123324396783": [{"hits_count_pro <= 0": [{"orf_len <= -0.8912506712510705": [{"HFI_normalized <= 112": ["ess", "non_ess"]}, {"insertion_index <= 0.005390835579514825": [{"orf_len <= 0.3684564796599992": [{"NI <= 0.02699748023517805": [{"NI <= 0.016584298853320596": [{"orf_len <= -0.7794584782048499": ["non_ess", {"orf_len <= -0.5395142589836939": ["ess", {"HFI_normalized <= 821": [{"orf_len <= -0.02417951542916537": ["ess", "non_ess"]}, "ess"]}]}]}, {"reads_count <= -0.4395397989100661": ["non_ess", "ess"]}]}, {"reads_count <= -0.4511411472389801": ["ess", {"HFI_normalized <= 126": ["non_ess", {"reads_count <= -0.3032239560453272": [{"HFI_normalized <= 442": [{"NI <= 0.12252726936587167": [{"insertion_index <= 0.0039946737683089215": ["ess", "non_ess"]}, "ess"]}, {"insertion_index <= 0.0012682308180088776": ["non_ess", {"insertion_index <= 0.0015661707126076742": ["ess", {"NI <= 0.13824015413536347": [{"insertion_index <= 0.004143646408839779": [{"NI <= 0.10704415648222072": [{"HFI_normalized <= 493": ["ess", {"HFI_normalized <= 500": ["non_ess", {"insertion_index <= 0.0019096117122851689": ["non_ess", "ess"]}]}]}, "non_ess"]}, "ess"]}, "non_ess"]}]}]}]}, "non_ess"]}]}]}]}, {"NI <= 0.045213837428898514": ["ess", {"HFI_normalized <= 1231": [{"HFI_normalized <= 547": [{"NI <= 0.06199926044619746": ["non_ess", "ess"]}, {"insertion_index <= 0.00427578834847675": [{"reads_count <= -0.3467290122787545": [{"HFI_normalized <= 948": ["non_ess", "ess"]}, {"NI <= 0.06592319332396157": ["non_ess", "ess"]}]}, "non_ess"]}]}, {"NI <= 0.04936549499159172": ["non_ess", "ess"]}]}]}]}, {"reads_count <= -0.2626192368941284": [{"reads_count <= -0.36413103477212544": [{"reads_count <= -0.4250381134989237": ["ess", "non_ess"]}, "ess"]}, {"reads_count <= 0.04771683090431975": ["non_ess", "ess"]}]}]}]}, {"NI <= 0.08026315789473684": [{"hits_count_pro <= 3": [{"orf_len <= -0.16051145816845866": [{"insertion_index <= 0.0034602076124567475": [{"HFI_normalized <= 217": ["ess", {"orf_len <= -0.4249954270826876": [{"HFI_normalized <= 554": [{"insertion_index <= 0.001314060446780552": [{"orf_len <= -0.7876383947692076": ["non_ess", {"orf_len <= -0.5258810647097646": ["non_ess", "ess"]}]}, {"orf_len <= -0.8721641992675694": ["ess", {"NI <= 0.03963527714815578": ["ess", "non_ess"]}]}]}, "ess"]}, "non_ess"]}]}, "ess"]}, {"orf_len <= 0.21576470379199075": ["ess", {"reads_count <= -0.4134367651700097": ["ess", "non_ess"]}]}]}, {"HFI_normalized <= 418": [{"orf_len <= -0.5040679538714776": ["non_ess", "ess"]}, "non_ess"]}]}, {"NI <= 0.32750695536470303": [{"reads_count <= -0.2887222706341848": [{"hits_count <= -0.32461863269451285": [{"insertion_index <= 0.004633204633204633": [{"orf_len <= -0.8094515056074946": ["non_ess", {"orf_len <= -0.040539348557880564": [{"insertion_index <= 0.004056795131845843": [{"insertion_index <= 0.0036697247706422025": [{"reads_count <= -0.4076360910055528": ["non_ess", "ess"]}, "ess"]}, {"insertion_index <= 0.004602991944764097": ["non_ess", "ess"]}]}, "non_ess"]}]}, "non_ess"]}, "ess"]}, "non_ess"]}, "ess"]}]}]}, {"hits_count <= 0.1382925010616921": [{"hits_count_pro <= 0": [{"NI <= 0.3589865229110513": [{"NI <= 0.3260611937082525": [{"HFI_normalized <= 403": [{"orf_len <= -0.3650093722773985": [{"orf_len <= -0.3731892888417561": [{"reads_count <= -0.4337391247456092": [{"orf_len <= -0.9539633649111454": ["non_ess", {"insertion_index <= 0.0060790273556231": ["non_ess", "ess"]}]}, {"NI <= 0.2443313738082301": [{"insertion_index <= 0.00911854103343465": ["non_ess", "ess"]}, "non_ess"]}]}, "ess"]}, "non_ess"]}, {"hits_count <= -0.09316306581641036": [{"HFI_normalized <= 493": ["ess", {"hits_count <= -0.2667547409749872": ["non_ess", {"orf_len <= 0.3929962293530721": ["ess", "non_ess"]}]}]}, "ess"]}]}, {"insertion_index <= 0.010706638115631693": ["ess", "non_ess"]}]}, {"reads_count <= -0.4163371022522382": ["ess", "non_ess"]}]}, {"HFI_normalized <= 586": [{"NI <= 0.3464677589361075": ["non_ess", {"NI <= 0.3472909471035057": ["ess", {"orf_len <= -0.7630986450761348": [{"orf_len <= -0.7658252839309206": [{"hits_count_pro <= 10": [{"NI <= 0.4971518987341772": [{"NI <= 0.4915997078159241": ["non_ess", "ess"]}, "non_ess"]}, {"HFI_normalized <= 119": [{"HFI_normalized <= 43": ["non_ess", "ess"]}, "non_ess"]}]}, "ess"]}, "non_ess"]}]}]}, {"reads_count <= -0.26841991105858537": ["non_ess", {"hits_count <= -0.15102695753593598": [{"hits_count <= -0.2667547409749872": ["non_ess", "ess"]}, "non_ess"]}]}]}]}, {"HFI_normalized <= 796": ["non_ess", {"NI <= 0.3377185251654462": ["non_ess", "ess"]}]}]}]}, {"insertion_index <= 0.00585480093676815": [{"hits_count_pro <= 2": [{"HFI_normalized <= 1309": [{"insertion_index <= 0.002325581395348837": [{"HFI_normalized <= 537": [{"reads_count <= -0.4105364280877813": [{"NI <= 0.05547265498638227": [{"hits_count_pro <= 0": [{"orf_len <= 0.21031142608241904": [{"reads_count <= -0.4482408101567516": [{"orf_len <= -0.7794584782048499": [{"orf_len <= -0.8667109215579977": [{"HFI_normalized <= 332": [{"HFI_normalized <= 198": [{"HFI_normalized <= 94": ["non_ess", "ess"]}, "non_ess"]}, "ess"]}, "non_ess"]}, {"HFI_normalized <= 465": ["ess", {"NI <= 0.0": ["ess", "non_ess"]}]}]}, "non_ess"]}, "ess"]}, {"HFI_normalized <= 433": [{"reads_count <= -0.4337391247456092": ["non_ess", "ess"]}, "ess"]}]}, "ess"]}, "non_ess"]}, {"hits_count <= -0.5560741995726153": [{"orf_len <= 1.3336866342541955": [{"reads_count <= -0.4105364280877813": [{"orf_len <= 0.05489301135962472": [{"HFI_normalized <= 751": [{"hits_count <= -0.7875297664507178": ["ess", "non_ess"]}, {"orf_len <= -0.18505120786153145": [{"orf_len <= -0.3213831506008247": [{"hits_count_pro <= 0": ["ess", "non_ess"]}, "non_ess"]}, "ess"]}]}, "ess"]}, {"insertion_index <= 0.0018326206475259624": [{"HFI_normalized <= 728": ["non_ess", "ess"]}, "ess"]}]}, "non_ess"]}, "non_ess"]}]}, {"HFI_normalized <= 208": ["non_ess", {"NI <= 0.045041692509131": ["ess", {"NI <= 0.06457504030589678": [{"HFI_normalized <= 985": ["non_ess", "ess"]}, {"NI <= 0.07255611495699603": ["ess", {"HFI_normalized <= 428": [{"HFI_normalized <= 315": [{"NI <= 0.10098655223937784": ["non_ess", {"insertion_index <= 0.0049400141143260395": [{"NI <= 0.19947621126145787": [{"NI <= 0.14277450628781654": [{"NI <= 0.11451564315531265": ["ess", "non_ess"]}, "ess"]}, "non_ess"]}, "ess"]}]}, {"hits_count <= 0.08042860934216649": [{"reads_count <= -0.19011080983841624": [{"hits_count_pro <= 0": ["ess", {"hits_count <= -0.7296658747311922": [{"NI <= 0.08026315789473684": ["ess", "non_ess"]}, "ess"]}]}, "non_ess"]}, "non_ess"]}]}, {"HFI_normalized <= 652": [{"NI <= 0.1420873305463596": [{"HFI_normalized <= 582": [{"hits_count_pro <= 0": [{"hits_count <= -0.7875297664507178": ["non_ess", "ess"]}, "non_ess"]}, "non_ess"]}, "non_ess"]}, {"HFI_normalized <= 824": [{"orf_len <= 0.4829753115610056": ["ess", {"reads_count <= -0.24811755148298595": [{"reads_count <= -0.3699317089365824": ["ess", "non_ess"]}, "ess"]}]}, {"NI <= 0.13451650988307878": [{"HFI_normalized <= 1228": ["non_ess", "ess"]}, {"NI <= 0.16977590648232688": [{"reads_count <= -0.4018354168410958": ["non_ess", "ess"]}, {"NI <= 0.2": ["non_ess", {"hits_count <= 0.022564717622640867": ["ess", "non_ess"]}]}]}]}]}]}]}]}]}]}]}]}, "ess"]}, {"hits_count_pro <= 3": [{"reads_count <= -0.3467290122787545": [{"hits_count <= -0.7296658747311922": [{"HFI_normalized <= 322": ["ess", "non_ess"]}, "ess"]}, "non_ess"]}, "non_ess"]}]}, {"hits_count <= -0.32461863269451285": [{"insertion_index <= 0.010121457489878544": [{"hits_count_pro <= 0": [{"hits_count <= -0.6718019830116665": [{"HFI_normalized <= 401": [{"insertion_index <= 0.009345794392523364": ["non_ess", "ess"]}, "ess"]}, {"reads_count <= -0.4047357539233243": ["ess", {"orf_len <= -0.2095909575546042": [{"orf_len <= -0.335016344874754": [{"orf_len <= -0.4604417321949038": [{"orf_len <= -0.6240400634820557": ["ess", "non_ess"]}, "ess"]}, "non_ess"]}, {"HFI_normalized <= 379": ["ess", {"HFI_normalized <= 468": ["non_ess", "ess"]}]}]}]}]}, {"insertion_index <= 0.00969529085872576": [{"HFI_normalized <= 265": [{"HFI_normalized <= 245": [{"HFI_normalized <= 206": ["non_ess", {"reads_count <= -0.32642665270315513": [{"HFI_normalized <= 207": ["ess", "non_ess"]}, "ess"]}]}, "ess"]}, "non_ess"]}, "ess"]}]}, {"NI <= 0.5359107751038586": [{"NI <= 0.5225087412587414": [{"NI <= 0.2509614601742362": [{"reads_count <= -0.36123069768989696": [{"orf_len <= -0.6076802303533405": ["non_ess", "ess"]}, "non_ess"]}, {"insertion_index <= 0.016483516483516484": ["non_ess", {"insertion_index <= 0.0169971671388102": ["ess", "non_ess"]}]}]}, "ess"]}, "non_ess"]}]}, {"hits_count_pro <= 1": [{"HFI_normalized <= 619": [{"orf_len <= 0.1257856215840572": [{"orf_len <= 0.04943973365005299": [{"hits_count <= 1.6427536857693583": [{"reads_count <= -0.24811755148298595": [{"reads_count <= -0.2742205852230423": ["non_ess", "ess"]}, "non_ess"]}, "ess"]}, {"reads_count <= -0.03349260739807789": ["ess", "non_ess"]}]}, "non_ess"]}, {"orf_len <= 1.0555694710660373": [{"hits_count_pro <= 0": [{"NI <= 0.4031159730115858": ["ess", "non_ess"]}, {"hits_count <= -0.15102695753593598": ["ess", "non_ess"]}]}, "non_ess"]}]}, "non_ess"]}]}]}, {"insertion_index <= 0.005575266092245312": [{"hits_count_pro <= 0": [{"orf_len <= -0.7221990622543468": [{"reads_count <= -0.4482408101567516": [{"orf_len <= -0.9430568094920021": ["ess", {"orf_len <= -0.8885240323962846": ["non_ess", {"NI <= 0.0": [{"HFI_normalized <= 325": ["non_ess", {"HFI_normalized <= 506": ["ess", "non_ess"]}]}, "ess"]}]}]}, "non_ess"]}, {"reads_count <= -0.29162260771641324": [{"HFI_normalized <= 837": [{"orf_len <= 0.6520269205577292": [{"HFI_normalized <= 615": [{"NI <= 0.19552280798611296": [{"HFI_normalized <= 191": ["non_ess", {"insertion_index <= 0.004878048780487805": [{"insertion_index <= 0.002034587995930824": [{"insertion_index <= 0.001784121320249777": [{"orf_len <= -0.6158601469176981": ["ess", {"orf_len <= -0.6049535914985547": ["non_ess", {"HFI_normalized <= 492": [{"HFI_normalized <= 465": ["ess", "non_ess"]}, "ess"]}]}]}, "non_ess"]}, "ess"]}, {"insertion_index <= 0.005095541401273885": [{"reads_count <= -0.3293269897853836": ["non_ess", "ess"]}, "ess"]}]}]}, {"NI <= 0.21737481031866465": ["non_ess", "ess"]}]}, {"hits_count <= -0.6718019830116665": [{"HFI_normalized <= 647": ["non_ess", {"orf_len <= -0.5213366666184548": ["ess", {"orf_len <= -0.3977290385348289": ["non_ess", {"orf_len <= -0.1168852364918848": ["ess", {"insertion_index <= 0.0010758472296933837": ["non_ess", "ess"]}]}]}]}]}, "ess"]}]}, {"HFI_normalized <= 636": ["non_ess", {"NI <= 0.0829373873601973": ["ess", "non_ess"]}]}]}, {"orf_len <= 0.3166503414190678": [{"orf_len <= 0.2212179815015625": [{"reads_count <= -0.45694182140343703": [{"HFI_normalized <= 1189": ["ess", "non_ess"]}, "ess"]}, "non_ess"]}, "ess"]}]}, {"HFI_normalized <= 475": ["non_ess", {"NI <= 0.06570645857546073": ["ess", {"reads_count <= -0.236516203154072": ["non_ess", {"NI <= 0.11870349781920808": ["ess", {"reads_count <= -0.14950609068721735": ["non_ess", "ess"]}]}]}]}]}]}]}, {"insertion_index <= 0.002477291494632535": [{"HFI_normalized <= 863": [{"HFI_normalized <= 244": ["ess", {"orf_len <= -0.2423106238120345": [{"reads_count <= -0.4540414843212086": [{"HFI_normalized <= 461": [{"insertion_index <= 0.0012531328320802006": ["non_ess", "ess"]}, {"reads_count <= -0.45694182140343703": ["ess", "non_ess"]}]}, "non_ess"]}, {"NI <= 0.03336519064231022": ["non_ess", "ess"]}]}]}, "ess"]}, {"orf_len <= 0.6493002817029433": [{"NI <= 0.05164050507295441": ["ess", {"insertion_index <= 0.004434589800443459": [{"HFI_normalized <= 486": ["non_ess", {"HFI_normalized <= 628": [{"hits_count_pro <= 1": ["non_ess", {"orf_len <= 0.2293978980659201": ["ess", "non_ess"]}]}, "non_ess"]}]}, "non_ess"]}]}, {"NI <= 0.1488243401269629": [{"insertion_index <= 0.003903708523096942": [{"HFI_normalized <= 1006": ["ess", "non_ess"]}, "non_ess"]}, {"NI <= 0.3532783765965772": ["ess", "non_ess"]}]}]}]}]}, {"hits_count_pro <= 1": [{"hits_count <= -0.4403464161335641": [{"orf_len <= -0.9266969763632869": ["non_ess", {"reads_count <= -0.08859901196041915": [{"insertion_index <= 0.010706638115631693": [{"orf_len <= -0.3022966786173236": [{"HFI_normalized <= 373": [{"HFI_normalized <= 223": [{"NI <= 0.17430290682523514": ["non_ess", {"orf_len <= -0.6812994794325589": ["ess", {"HFI_normalized <= 181": ["non_ess", "ess"]}]}]}, {"hits_count_pro <= 0": ["ess", {"HFI_normalized <= 267": ["ess", "non_ess"]}]}]}, {"reads_count <= -0.4105364280877813": ["ess", "non_ess"]}]}, "non_ess"]}, "non_ess"]}, "ess"]}]}, {"insertion_index <= 0.008092485549132947": [{"hits_count <= 0.311884176220269": [{"orf_len <= 1.9853533205480167": [{"insertion_index <= 0.0061570035915854285": ["non_ess", {"reads_count <= -0.2075128323317872": [{"HFI_normalized <= 563": [{"insertion_index <= 0.007742703990470519": [{"hits_count <= -0.2088908492554616": ["ess", "non_ess"]}, "ess"]}, "ess"]}, {"insertion_index <= 0.006893580353295993": [{"HFI_normalized <= 386": ["non_ess", "ess"]}, "non_ess"]}]}]}, "ess"]}, "non_ess"]}, {"NI <= 0.4052964881980426": ["non_ess", {"NI <= 0.4120993764708737": [{"insertion_index <= 0.012178619756427604": ["ess", "non_ess"]}, {"orf_len <= -0.4113622328087582": [{"HFI_normalized <= 258": [{"hits_count <= 1.5270259023303068": ["non_ess", "ess"]}, {"NI <= 0.532608695652174": ["non_ess", "ess"]}]}, "non_ess"]}]}]}]}]}, {"orf_len <= -0.7630986450761348": [{"hits_count_pro <= 2": [{"orf_len <= -0.7876383947692076": [{"NI <= 1.4263558282208588": [{"orf_len <= -0.8939773101058563": ["non_ess", {"orf_len <= -0.8585310049936401": ["ess", "non_ess"]}]}, "ess"]}, "ess"]}, {"reads_count <= -0.4337391247456092": [{"NI <= 0.25058584948174856": ["non_ess", "ess"]}, "non_ess"]}]}, "non_ess"]}]}]}, {"insertion_index <= 0.006616257088846882": [{"hits_count_pro <= 0": [{"reads_count <= -0.3525296864432115": [{"orf_len <= -0.8885240323962846": [{"insertion_index <= 0.006493506493506494": [{"HFI_normalized <= 112": ["ess", "non_ess"]}, "ess"]}, {"orf_len <= -0.3241097894556105": [{"orf_len <= -0.6249489431003177": [{"orf_len <= -0.7740052004952783": [{"insertion_index <= 0.0022883295194508014": [{"orf_len <= -0.7821851170596359": [{"insertion_index <= 0.0020876826722338203": ["ess", "non_ess"]}, "non_ess"]}, "ess"]}, "ess"]}, {"NI <= 0.1793467305855236": [{"insertion_index <= 0.004390779363336993": [{"insertion_index <= 0.003099173553719009": [{"insertion_index <= 0.0": [{"orf_len <= -0.3840958442608995": [{"orf_len <= -0.4240865474644256": [{"HFI_normalized <= 570": ["ess", "non_ess"]}, "ess"]}, {"HFI_normalized <= 378": ["ess", "non_ess"]}]}, {"HFI_normalized <= 588": ["non_ess", "ess"]}]}, "ess"]}, "non_ess"]}, "ess"]}]}, {"reads_count <= -0.4105364280877813": [{"orf_len <= 0.33301017454778303": ["ess", {"insertion_index <= 0.0016906170752324595": ["ess", "non_ess"]}]}, {"insertion_index <= 0.002170767004341534": [{"HFI_normalized <= 728": ["non_ess", "ess"]}, {"hits_count <= -0.6139380912921409": ["ess", {"HFI_normalized <= 824": ["ess", {"NI <= 0.1125376439698345": ["non_ess", "ess"]}]}]}]}]}]}]}, {"NI <= 0.1709403290088124": [{"HFI_normalized <= 273": ["non_ess", {"HFI_normalized <= 1287": [{"reads_count <= -0.3293269897853836": [{"NI <= 0.10562311316762124": [{"orf_len <= 0.4829753115610056": ["ess", "non_ess"]}, "non_ess"]}, {"insertion_index <= 0.005458956732713303": [{"reads_count <= -0.14950609068721735": [{"HFI_normalized <= 701": [{"reads_count <= -0.2771209223052708": ["non_ess", "ess"]}, "ess"]}, "non_ess"]}, "ess"]}]}, "ess"]}]}, {"HFI_normalized <= 918": [{"HFI_normalized <= 309": [{"HFI_normalized <= 288": ["non_ess", "ess"]}, "non_ess"]}, "ess"]}]}]}, {"insertion_index <= 0.002477291494632535": [{"HFI_normalized <= 461": [{"NI <= 0.05960774439035309": [{"hits_count <= -0.8453936581702434": [{"orf_len <= -0.8721641992675694": [{"orf_len <= -0.9757764757494324": ["non_ess", "ess"]}, "non_ess"]}, "ess"]}, "ess"]}, "ess"]}, {"NI <= 0.20862135707570645": [{"NI <= 0.1916609271523179": [{"insertion_index <= 0.004434589800443459": [{"hits_count_pro <= 2": [{"insertion_index <= 0.0030959752321981426": ["non_ess", {"insertion_index <= 0.003170577045022195": ["ess", {"insertion_index <= 0.003846153846153847": [{"orf_len <= 1.868107849792225": ["non_ess", "ess"]}, {"NI <= 0.10719365982523878": ["ess", "non_ess"]}]}]}]}, "non_ess"]}, {"orf_len <= -0.9212436986537148": ["ess", "non_ess"]}]}, "ess"]}, "non_ess"]}]}]}, {"reads_count <= -0.3206259785386981": [{"HFI_normalized <= 134": ["non_ess", {"hits_count_pro <= 2": [{"insertion_index <= 0.0073937153419593345": ["non_ess", {"reads_count <= -0.3235263156209266": [{"reads_count <= -0.3960347426766388": [{"hits_count_pro <= 1": [{"hits_count <= -0.6718019830116665": ["non_ess", "ess"]}, "non_ess"]}, {"NI <= 0.4360944821189821": [{"NI <= 0.2048645729478232": [{"HFI_normalized <= 279": ["non_ess", "ess"]}, "non_ess"]}, {"reads_count <= -0.3525296864432115": ["ess", "non_ess"]}]}]}, "ess"]}]}, {"orf_len <= 0.005813511973479146": [{"hits_count_pro <= 10": ["non_ess", {"orf_len <= -0.7685519227857065": ["ess", "non_ess"]}]}, "ess"]}]}]}, {"hits_count <= 0.4276119596593202": [{"HFI_normalized <= 293": [{"NI <= 1.965711175616836": [{"orf_len <= -0.8857973935414988": [{"orf_len <= -0.8912506712510705": [{"NI <= 0.5359107751038586": [{"NI <= 0.514317617866005": ["non_ess", "ess"]}, "non_ess"]}, "ess"]}, {"orf_len <= 0.09306595532662684": ["non_ess", {"orf_len <= 0.1257856215840572": ["ess", "non_ess"]}]}]}, "ess"]}, {"hits_count_pro <= 0": [{"orf_len <= -0.7876383947692076": ["ess", {"reads_count <= -0.2568185627296714": ["non_ess", {"reads_count <= -0.25101788856521445": ["ess", {"HFI_normalized <= 420": [{"reads_count <= -0.24811755148298595": ["ess", "non_ess"]}, {"reads_count <= -0.05089462989144882": [{"orf_len <= 0.3602765630956416": [{"HFI_normalized <= 600": ["non_ess", "ess"]}, "non_ess"]}, "ess"]}]}]}]}]}, {"HFI_normalized <= 954": [{"HFI_normalized <= 297": ["ess", "non_ess"]}, "ess"]}]}]}, {"insertion_index <= 0.09060402684563758": ["non_ess", {"HFI_normalized <= 96": ["non_ess", "ess"]}]}]}]}]}, {"insertion_index <= 0.005519779208831647": [{"hits_count_pro <= 1": [{"HFI_normalized <= 1309": [{"reads_count <= -0.2104131694140156": [{"orf_len <= -0.9239703375085008": [{"HFI_normalized <= 112": ["ess", "non_ess"]}, {"HFI_normalized <= 1219": [{"HFI_normalized <= 150": ["non_ess", {"insertion_index <= 0.005129958960328317": [{"insertion_index <= 0.0010526315789473684": [{"insertion_index <= 0.0007616146230007616": [{"orf_len <= -0.8667109215579977": ["ess", {"orf_len <= -0.8121781444622804": ["non_ess", {"HFI_normalized <= 746": [{"orf_len <= -0.4059089550991865": [{"orf_len <= -0.7140191456899893": [{"orf_len <= -0.7203813030178229": ["ess", "non_ess"]}, "ess"]}, "ess"]}, {"orf_len <= -0.02417951542916537": [{"HFI_normalized <= 953": ["non_ess", "ess"]}, "ess"]}]}]}]}, "ess"]}, {"NI <= 0.03274876017783618": ["non_ess", {"orf_len <= 0.9056043340528146": [{"HFI_normalized <= 799": [{"HFI_normalized <= 523": [{"hits_count_pro <= 0": [{"insertion_index <= 0.003908794788273616": [{"reads_count <= -0.4511411472389801": ["ess", {"NI <= 0.1781966172483552": [{"reads_count <= -0.4163371022522382": ["ess", "non_ess"]}, "ess"]}]}, {"NI <= 0.2070056248538776": ["ess", "non_ess"]}]}, {"HFI_normalized <= 178": ["ess", "non_ess"]}]}, {"insertion_index <= 0.004337349397590362": [{"orf_len <= 0.056710770596148624": [{"HFI_normalized <= 542": ["ess", {"NI <= 0.04203130777764082": ["non_ess", "ess"]}]}, "ess"]}, "non_ess"]}]}, "ess"]}, {"orf_len <= 1.0855624984686818": ["non_ess", {"HFI_normalized <= 1159": [{"reads_count <= -0.32642665270315513": ["non_ess", {"NI <= 0.12999025132558195": [{"HFI_normalized <= 934": ["ess", "non_ess"]}, "non_ess"]}]}, "ess"]}]}]}]}]}, "ess"]}]}, "non_ess"]}]}, {"NI <= 0.1894072890762669": [{"reads_count <= -0.03349260739807789": ["non_ess", "ess"]}, "ess"]}]}, {"HFI_normalized <= 1583": ["ess", {"HFI_normalized <= 1668": [{"insertion_index <= 0.002276751834050089": ["ess", "non_ess"]}, "ess"]}]}]}, {"orf_len <= -0.1005254033631696": ["non_ess", {"insertion_index <= 0.003939592908732764": [{"orf_len <= 0.4093560624817872": ["ess", {"hits_count_pro <= 2": ["ess", "non_ess"]}]}, {"NI <= 0.20371333295653649": ["non_ess", "ess"]}]}]}]}, {"hits_count <= 0.022564717622640867": [{"hits_count_pro <= 0": [{"HFI_normalized <= 428": [{"reads_count <= -0.3786327201832679": [{"orf_len <= -0.9376035317824302": ["non_ess", {"NI <= 0.2810191004690805": [{"NI <= 0.2341089906489279": [{"HFI_normalized <= 154": ["ess", {"HFI_normalized <= 192": ["non_ess", {"orf_len <= -0.8530777272840684": ["non_ess", "ess"]}]}]}, "non_ess"]}, "ess"]}]}, {"HFI_normalized <= 283": ["non_ess", {"insertion_index <= 0.015690376569037656": [{"insertion_index <= 0.007773851590106007": [{"NI <= 0.20257614678899089": ["non_ess", "ess"]}, "non_ess"]}, "ess"]}]}]}, {"insertion_index <= 0.008181818181818179": [{"HFI_normalized <= 638": [{"reads_count <= -0.3815330572654964": ["ess", {"hits_count <= -0.2667547409749872": [{"NI <= 0.10993811561324413": ["ess", "non_ess"]}, "ess"]}]}, "non_ess"]}, "ess"]}]}, {"hits_count <= -0.15102695753593598": [{"hits_count_pro <= 11": [{"HFI_normalized <= 161": ["non_ess", {"HFI_normalized <= 162": ["ess", {"orf_len <= -0.7876383947692076": ["non_ess", {"orf_len <= -0.7630986450761348": [{"HFI_normalized <= 267": ["ess", "non_ess"]}, {"insertion_index <= 0.011350737797956869": [{"insertion_index <= 0.010923535253227408": [{"insertion_index <= 0.009776536312849162": [{"HFI_normalized <= 395": [{"insertion_index <= 0.007373271889400922": ["non_ess", {"reads_count <= -0.1872104727561877": [{"insertion_index <= 0.008342022940563087": [{"orf_len <= -0.34592290029389744": [{"NI <= 0.28047011752938233": ["non_ess", "ess"]}, {"hits_count_pro <= 6": ["non_ess", "ess"]}]}, "non_ess"]}, "ess"]}]}, {"orf_len <= 0.6356670874290141": ["non_ess", {"HFI_normalized <= 549": ["ess", "non_ess"]}]}]}, "non_ess"]}, "ess"]}, "non_ess"]}]}]}]}]}, {"hits_count <= -0.4982103078530897": ["non_ess", "ess"]}]}, "non_ess"]}]}, {"HFI_normalized <= 507": ["non_ess", {"HFI_normalized <= 510": ["ess", {"HFI_normalized <= 1739": [{"NI <= 0.3736889740722994": ["non_ess", {"NI <= 0.4031159730115858": ["ess", "non_ess"]}]}, "ess"]}]}]}]}]}, {"insertion_index <= 0.0058762530245419975": [{"hits_count_pro <= 0": [{"orf_len <= -0.9157904209441432": [{"hits_count <= -0.9032575498897693": [{"HFI_normalized <= 198": ["ess", "non_ess"]}, "non_ess"]}, {"NI <= 0.1825685618729097": [{"HFI_normalized <= 1376": [{"orf_len <= -0.5340609812741222": [{"orf_len <= -0.7221990622543468": [{"insertion_index <= 0.0036697247706422025": [{"insertion_index <= 0.002386634844868735": [{"HFI_normalized <= 155": ["non_ess", "ess"]}, {"orf_len <= -0.9076105043797856": ["ess", "non_ess"]}]}, "ess"]}, "ess"]}, {"orf_len <= -0.3977290385348289": [{"orf_len <= -0.4386286213566168": [{"orf_len <= -0.4495351767757603": [{"reads_count <= -0.36413103477212544": [{"orf_len <= -0.5231544258549787": ["ess", "non_ess"]}, "ess"]}, {"NI <= 0.022444878632169603": ["non_ess", "ess"]}]}, "non_ess"]}, {"reads_count <= -0.14950609068721735": [{"insertion_index <= 0.004266991770801585": [{"HFI_normalized <= 232": ["non_ess", {"insertion_index <= 0.004187285877426722": [{"orf_len <= -0.1986844021354608": [{"hits_count <= -0.9032575498897693": ["non_ess", "ess"]}, {"orf_len <= 0.03853317823090953": [{"NI <= 0.07830504659258944": [{"orf_len <= 0.008540150828265012": [{"HFI_normalized <= 604": ["ess", {"orf_len <= -0.10597868107274132": ["ess", "non_ess"]}]}, "non_ess"]}, "non_ess"]}, {"insertion_index <= 0.0035545023696682467": [{"reads_count <= -0.3989350797588673": [{"hits_count <= -0.7296658747311922": [{"insertion_index <= 0.0005458515283842794": ["ess", {"HFI_normalized <= 501": ["ess", "non_ess"]}]}, "ess"]}, {"reads_count <= -0.3931344055944103": ["non_ess", {"NI <= 0.06370805628575847": ["ess", {"reads_count <= -0.3583303606076685": ["ess", "non_ess"]}]}]}]}, "ess"]}]}]}, "non_ess"]}]}, {"reads_count <= -0.2278151919073865": ["ess", "non_ess"]}]}, {"insertion_index <= 0.005677517032551098": ["non_ess", "ess"]}]}]}]}, "ess"]}, {"orf_len <= -0.4331753436470451": [{"orf_len <= -0.6185867857724839": ["non_ess", "ess"]}, {"reads_count <= -0.17850946150950225": ["non_ess", "ess"]}]}]}]}, {"hits_count_pro <= 4": [{"HFI_normalized <= 288": [{"insertion_index <= 0.005675368898978434": ["non_ess", "ess"]}, {"HFI_normalized <= 934": [{"NI <= 0.09010957342171044": [{"insertion_index <= 0.002926115581565472": [{"hits_count_pro <= 3": [{"HFI_normalized <= 297": ["ess", {"orf_len <= 0.027626622811766068": [{"reads_count <= -0.4540414843212086": [{"orf_len <= -0.4086355939539724": [{"insertion_index <= 0.0011235955056179776": ["non_ess", "ess"]}, "ess"]}, "non_ess"]}, "ess"]}]}, "ess"]}, "ess"]}, {"NI <= 0.13215215960156854": ["non_ess", {"NI <= 0.13863040831906245": ["ess", {"hits_count <= -0.6718019830116665": ["ess", {"HFI_normalized <= 410": [{"hits_count_pro <= 1": ["non_ess", "ess"]}, "non_ess"]}]}]}]}]}, {"NI <= 0.04454606106492553": ["ess", "non_ess"]}]}]}, "non_ess"]}]}, {"hits_count_pro <= 0": [{"insertion_index <= 0.01152073732718894": [{"hits_count <= -0.5560741995726153": [{"hits_count <= -0.6718019830116665": [{"NI <= 0.325521503991759": [{"HFI_normalized <= 326": [{"orf_len <= -0.940330170637216": ["ess", "non_ess"]}, "ess"]}, "ess"]}, {"reads_count <= -0.4250381134989237": ["non_ess", {"HFI_normalized <= 173": [{"HFI_normalized <= 164": ["ess", "non_ess"]}, "ess"]}]}]}, {"HFI_normalized <= 316": ["non_ess", {"orf_len <= 1.0555694710660373": [{"HFI_normalized <= 579": [{"NI <= 0.205613247073112": [{"insertion_index <= 0.0063145809414466144": ["non_ess", {"hits_count <= -0.4403464161335641": ["non_ess", {"NI <= 0.14739245727754866": ["non_ess", "ess"]}]}]}, {"HFI_normalized <= 320": ["ess", "non_ess"]}]}, {"insertion_index <= 0.006470881035340966": ["non_ess", {"HFI_normalized <= 1292": ["ess", "non_ess"]}]}]}, "non_ess"]}]}]}, {"hits_count <= -0.4982103078530897": [{"orf_len <= -0.8612576438484258": ["non_ess", {"reads_count <= -0.3003236189630987": [{"NI <= 0.35283251231527096": ["ess", "non_ess"]}, "ess"]}]}, "non_ess"]}]}, {"orf_len <= -0.7630986450761348": [{"orf_len <= -0.7876383947692076": [{"hits_count_pro <= 10": [{"orf_len <= -0.9594166426207172": [{"reads_count <= -0.04219361864476336": ["non_ess", "ess"]}, "non_ess"]}, {"NI <= 0.8132080685272174": ["ess", "non_ess"]}]}, {"HFI_normalized <= 140": ["non_ess", {"NI <= 0.1954565096610902": ["non_ess", "ess"]}]}]}, {"HFI_normalized <= 1080": [{"insertion_index <= 0.012178619756427604": [{"insertion_index <= 0.012100677637947723": [{"HFI_normalized <= 237": [{"HFI_normalized <= 235": ["non_ess", "ess"]}, "non_ess"]}, "ess"]}, "non_ess"]}, "ess"]}]}]}]}, {"insertion_index <= 0.005898123324396783": [{"HFI_normalized <= 1309": [{"hits_count_pro <= 0": [{"reads_count <= -0.04219361864476336": [{"HFI_normalized <= 1282": [{"orf_len <= -0.839444533010139": [{"insertion_index <= 0.0": [{"HFI_normalized <= 229": ["ess", {"HFI_normalized <= 325": ["non_ess", "ess"]}]}, "non_ess"]}, {"HFI_normalized <= 241": ["ess", {"NI <= 0.1910223770601635": [{"NI <= 0.16469023163399885": [{"reads_count <= -0.1959114840028732": [{"hits_count <= -0.3824825244140385": [{"NI <= 0.16435071500794454": [{"orf_len <= 1.0746559430495384": [{"orf_len <= 0.6438470039933716": [{"hits_count <= -0.7875297664507178": [{"orf_len <= -0.6676662851586296": [{"HFI_normalized <= 247": ["non_ess", "ess"]}, {"insertion_index <= 0.0020222446916076846": [{"orf_len <= -0.4240865474644256": ["non_ess", "ess"]}, "non_ess"]}]}, {"insertion_index <= 0.005390835579514825": [{"orf_len <= -0.6703929240134154": ["non_ess", {"reads_count <= -0.3032239560453272": ["ess", "non_ess"]}]}, "non_ess"]}]}, {"HFI_normalized <= 695": [{"orf_len <= 0.8892445009240995": ["non_ess", "ess"]}, "non_ess"]}]}, "ess"]}, "non_ess"]}, {"orf_len <= 2.132591818706454": [{"NI <= 0.15664462360721082": [{"NI <= 0.052739198384088574": ["ess", "non_ess"]}, "ess"]}, "ess"]}]}, {"reads_count <= -0.1031006973715616": ["non_ess", "ess"]}]}, "ess"]}, {"NI <= 0.2051894160905544": ["non_ess", {"NI <= 0.24708742086253546": ["ess", {"NI <= 0.29845388306379955": ["non_ess", "ess"]}]}]}]}]}]}, "non_ess"]}, "non_ess"]}, {"HFI_normalized <= 970": [{"reads_count <= -0.2887222706341848": [{"insertion_index <= 0.004860267314702308": [{"insertion_index <= 0.004612850082372322": [{"orf_len <= 0.027626622811766068": [{"orf_len <= -0.3213831506008247": [{"HFI_normalized <= 681": [{"hits_count_pro <= 3": [{"hits_count_pro <= 2": [{"orf_len <= -0.8721641992675694": [{"orf_len <= -0.8748908381223552": ["non_ess", "ess"]}, "non_ess"]}, {"orf_len <= -0.5667806475315526": ["non_ess", "ess"]}]}, "non_ess"]}, "ess"]}, "non_ess"]}, {"HFI_normalized <= 489": ["non_ess", {"reads_count <= -0.3786327201832679": ["ess", {"reads_count <= -0.3148253043742412": ["non_ess", "ess"]}]}]}]}, {"orf_len <= -0.4658950099044755": ["ess", "non_ess"]}]}, "non_ess"]}, "non_ess"]}, {"insertion_index <= 0.0033287101248266303": [{"hits_count_pro <= 2": ["ess", "non_ess"]}, "non_ess"]}]}]}, {"NI <= 0.11649955508260786": [{"hits_count_pro <= 1": [{"hits_count <= -0.2667547409749872": ["ess", "non_ess"]}, "non_ess"]}, "non_ess"]}]}, {"insertion_index <= 0.010121457489878544": [{"hits_count_pro <= 0": [{"reads_count <= -0.3786327201832679": [{"orf_len <= -0.8176314221718521": [{"NI <= 0.2878059440559441": ["non_ess", "ess"]}, {"insertion_index <= 0.005917159763313609": ["non_ess", {"hits_count <= -0.4982103078530897": ["ess", "non_ess"]}]}]}, {"HFI_normalized <= 816": [{"NI <= 0.2469518716577541": [{"orf_len <= 0.1748651209702028": [{"insertion_index <= 0.008037508372404554": [{"hits_count <= -0.3824825244140385": ["non_ess", "ess"]}, "ess"]}, "non_ess"]}, {"orf_len <= 1.0473895545016796": ["non_ess", {"NI <= 0.4088607854811226": ["non_ess", "ess"]}]}]}, "ess"]}]}, {"NI <= 0.221438263229308": ["non_ess", {"NI <= 0.2239193841040512": ["ess", {"NI <= 0.2987254773655081": [{"HFI_normalized <= 575": [{"NI <= 0.2962558973572169": [{"insertion_index <= 0.009438909281594129": ["non_ess", {"hits_count_pro <= 1": ["non_ess", "ess"]}]}, "ess"]}, "ess"]}, "non_ess"]}]}]}]}, {"hits_count <= 0.1382925010616921": [{"HFI_normalized <= 634": [{"hits_count_pro <= 11": [{"hits_count_pro <= 1": [{"NI <= 0.18647579095286312": ["ess", {"reads_count <= -0.3525296864432115": [{"orf_len <= -0.6622130074490578": ["non_ess", "ess"]}, {"reads_count <= -0.03639294448030638": ["non_ess", {"HFI_normalized <= 240": ["non_ess", "ess"]}]}]}]}, "non_ess"]}, {"reads_count <= -0.15530676485167436": ["non_ess", {"insertion_index <= 0.0364741641337386": ["ess", "non_ess"]}]}]}, "ess"]}, "non_ess"]}]}]}, {"NI <= 0.1475743555849306": [{"hits_count_pro <= 0": [{"orf_len <= -0.839444533010139": [{"HFI_normalized <= 197": [{"reads_count <= -0.4540414843212086": [{"orf_len <= -1.0739354745217236": ["non_ess", "ess"]}, "non_ess"]}, "non_ess"]}, {"HFI_normalized <= 1228": [{"HFI_normalized <= 208": ["non_ess", {"reads_count <= -0.4482408101567516": [{"orf_len <= -0.3868224831156855": ["ess", {"orf_len <= -0.37864256655132783": ["non_ess", {"HFI_normalized <= 884": ["ess", {"orf_len <= -0.18505120786153145": [{"orf_len <= -0.3213831506008247": ["ess", "non_ess"]}, "ess"]}]}]}]}, {"insertion_index <= 0.0016357688113413304": [{"HFI_normalized <= 709": ["non_ess", {"orf_len <= -0.456806213721856": ["non_ess", "ess"]}]}, {"reads_count <= -0.3525296864432115": [{"HFI_normalized <= 985": [{"HFI_normalized <= 961": [{"HFI_normalized <= 877": [{"HFI_normalized <= 725": [{"HFI_normalized <= 537": [{"HFI_normalized <= 466": [{"insertion_index <= 0.0030349013657056147": ["ess", {"orf_len <= -0.7658252839309206": ["ess", {"reads_count <= -0.4453404730745231": ["non_ess", {"NI <= 0.13815668202764975": ["ess", "non_ess"]}]}]}]}, "non_ess"]}, "ess"]}, "non_ess"]}, "ess"]}, "non_ess"]}, "ess"]}, {"reads_count <= -0.3322273268676121": [{"insertion_index <= 0.0037626628075253256": ["non_ess", "ess"]}, {"HFI_normalized <= 824": [{"NI <= 0.13319952379546818": [{"hits_count <= -0.4403464161335641": [{"hits_count <= -0.6139380912921409": ["ess", "non_ess"]}, "ess"]}, {"orf_len <= 0.05216637250483885": ["ess", "non_ess"]}]}, "non_ess"]}]}]}]}]}]}, "ess"]}]}, {"HFI_normalized <= 389": [{"NI <= 0.09154292502398684": [{"hits_count_pro <= 6": [{"HFI_normalized <= 366": ["non_ess", {"insertion_index <= 0.0": ["non_ess", "ess"]}]}, "ess"]}, "non_ess"]}, {"NI <= 0.012715522880092095": ["ess", {"insertion_index <= 0.004633204633204633": [{"orf_len <= -0.1986844021354608": [{"orf_len <= -0.5695072863863384": ["ess", "non_ess"]}, {"hits_count_pro <= 4": [{"NI <= 0.059342962970664034": ["ess", {"NI <= 0.13215215960156854": [{"HFI_normalized <= 642": ["non_ess", {"NI <= 0.09010957342171044": ["ess", "non_ess"]}]}, "ess"]}]}, "non_ess"]}]}, "non_ess"]}]}]}]}, {"hits_count <= 0.08042860934216649": [{"reads_count <= -0.3815330572654964": [{"hits_count_pro <= 0": [{"hits_count <= -0.4982103078530897": [{"insertion_index <= 0.00997506234413965": [{"HFI_normalized <= 154": ["ess", {"HFI_normalized <= 208": ["non_ess", {"HFI_normalized <= 230": ["ess", {"reads_count <= -0.3902340685121817": [{"NI <= 0.17057611426313266": ["ess", "non_ess"]}, "ess"]}]}]}]}, "non_ess"]}, "ess"]}, {"NI <= 0.20862135707570645": [{"reads_count <= -0.4134367651700097": [{"HFI_normalized <= 181": ["non_ess", {"NI <= 0.17556475054692594": ["non_ess", {"hits_count <= -0.5560741995726153": ["ess", "non_ess"]}]}]}, "non_ess"]}, {"insertion_index <= 0.011278195488721804": ["non_ess", {"NI <= 0.30140510918416785": ["ess", "non_ess"]}]}]}]}, {"HFI_normalized <= 883": [{"hits_count_pro <= 0": [{"HFI_normalized <= 149": ["non_ess", {"HFI_normalized <= 159": ["ess", {"HFI_normalized <= 218": ["non_ess", {"insertion_index <= 0.004552352048558422": ["non_ess", {"insertion_index <= 0.004814305364511692": ["ess", {"orf_len <= -0.6594863685942719": [{"insertion_index <= 0.01152073732718894": ["ess", "non_ess"]}, {"hits_count <= 0.022564717622640867": [{"HFI_normalized <= 221": ["ess", {"HFI_normalized <= 305": ["non_ess", {"HFI_normalized <= 320": ["ess", {"insertion_index <= 0.010309278350515464": [{"HFI_normalized <= 563": ["non_ess", "ess"]}, "ess"]}]}]}]}, "ess"]}]}]}]}]}]}]}, {"hits_count_pro <= 10": [{"hits_count_pro <= 3": [{"insertion_index <= 0.009019165727170236": [{"orf_len <= -0.34592290029389744": [{"orf_len <= -0.4440818990661886": ["non_ess", "ess"]}, {"orf_len <= 0.9056043340528146": ["non_ess", {"orf_len <= 0.9983100551155341": ["ess", "non_ess"]}]}]}, "non_ess"]}, "non_ess"]}, {"orf_len <= -0.9021572266702141": ["ess", "non_ess"]}]}]}, {"HFI_normalized <= 1187": ["ess", "non_ess"]}]}]}, "non_ess"]}]}, {"insertion_index <= 0.0063025210084033615": [{"hits_count_pro <= 0": [{"insertion_index <= 0.0032573289902280127": [{"HFI_normalized <= 1136": [{"orf_len <= -0.9321502540728585": ["non_ess", {"reads_count <= -0.2133135064962441": [{"orf_len <= 0.8210785295544528": [{"HFI_normalized <= 780": [{"HFI_normalized <= 513": [{"HFI_normalized <= 509": [{"NI <= 0.0": ["ess", {"insertion_index <= 0.001483679525222552": ["non_ess", {"HFI_normalized <= 408": [{"insertion_index <= 0.0022883295194508014": [{"orf_len <= 0.03853317823090953": ["non_ess", "ess"]}, {"insertion_index <= 0.0029651593773165306": ["ess", "non_ess"]}]}, "ess"]}]}]}, "non_ess"]}, {"insertion_index <= 0.0018326206475259624": [{"reads_count <= -0.4424401359922946": ["ess", "non_ess"]}, "ess"]}]}, {"NI <= 0.0": ["non_ess", {"orf_len <= -0.05689918168659575": ["ess", {"HFI_normalized <= 824": ["ess", "non_ess"]}]}]}]}, "ess"]}, "non_ess"]}]}, {"NI <= 0.024894475814568016": [{"NI <= 0.021846425841858585": ["ess", "non_ess"]}, "ess"]}]}, {"reads_count <= -0.4047357539233243": [{"reads_count <= -0.4366394618278376": [{"insertion_index <= 0.005141388174807198": [{"NI <= 0.11807443094719755": [{"orf_len <= -0.7440121730926338": ["non_ess", "ess"]}, "ess"]}, "non_ess"]}, {"HFI_normalized <= 310": [{"orf_len <= -0.4413552602114028": ["ess", "non_ess"]}, "ess"]}]}, {"insertion_index <= 0.0035149384885764497": ["non_ess", {"orf_len <= 0.056710770596148624": [{"HFI_normalized <= 248": [{"HFI_normalized <= 208": ["non_ess", "ess"]}, {"NI <= 0.26835672916462155": ["non_ess", "ess"]}]}, {"hits_count <= -0.32461863269451285": [{"insertion_index <= 0.004896626768226333": [{"NI <= 0.1825609756097561": [{"NI <= 0.07212314664516903": ["non_ess", "ess"]}, "non_ess"]}, "ess"]}, {"insertion_index <= 0.004283137962128043": ["non_ess", {"HFI_normalized <= 633": ["non_ess", {"orf_len <= 1.783582045293863": [{"NI <= 0.1832145736804948": ["non_ess", "ess"]}, "ess"]}]}]}]}]}]}]}]}, {"hits_count_pro <= 4": [{"NI <= 0.09010957342171044": [{"orf_len <= -0.7821851170596359": [{"NI <= 0.06344022845587331": ["non_ess", "ess"]}, {"HFI_normalized <= 945": [{"HFI_normalized <= 280": ["ess", {"HFI_normalized <= 311": ["non_ess", {"NI <= 0.08662387968260556": [{"orf_len <= 0.21576470379199075": [{"orf_len <= -0.1005254033631696": [{"insertion_index <= 0.0024410089503661514": [{"insertion_index <= 0.0": [{"HFI_normalized <= 554": ["non_ess", "ess"]}, "non_ess"]}, {"NI <= 0.08452678755273614": ["ess", "non_ess"]}]}, "ess"]}, "non_ess"]}, "ess"]}]}]}, "ess"]}]}, {"NI <= 0.3526145280177538": [{"insertion_index <= 0.003846153846153847": ["non_ess", {"insertion_index <= 0.003939592908732764": ["ess", {"HFI_normalized <= 513": [{"HFI_normalized <= 500": [{"NI <= 0.13215215960156854": ["non_ess", {"orf_len <= -0.9212436986537148": ["ess", {"HFI_normalized <= 304": ["non_ess", {"insertion_index <= 0.00547680412371134": [{"NI <= 0.22237325236548508": [{"HFI_normalized <= 410": ["ess", "non_ess"]}, "non_ess"]}, "non_ess"]}]}]}]}, "ess"]}, "non_ess"]}]}]}, "ess"]}]}, "non_ess"]}]}, {"hits_count <= 0.1382925010616921": [{"hits_count_pro <= 0": [{"HFI_normalized <= 299": [{"insertion_index <= 0.010471204188481676": [{"orf_len <= -0.5231544258549787": [{"insertion_index <= 0.008695652173913044": [{"insertion_index <= 0.007194244604316547": ["ess", "non_ess"]}, {"reads_count <= -0.4105364280877813": [{"insertion_index <= 0.00911854103343465": ["ess", "non_ess"]}, "ess"]}]}, "non_ess"]}, "non_ess"]}, {"HFI_normalized <= 329": ["ess", {"HFI_normalized <= 772": [{"hits_count <= -0.2088908492554616": [{"insertion_index <= 0.011398963730569948": [{"NI <= 0.2508407024536057": [{"insertion_index <= 0.008181818181818179": [{"NI <= 0.2115891428455882": [{"orf_len <= -0.3595560945678268": ["ess", "non_ess"]}, "ess"]}, "ess"]}, "non_ess"]}, "ess"]}, "non_ess"]}, "ess"]}]}]}, {"orf_len <= -0.8585310049936401": [{"hits_count_pro <= 9": [{"insertion_index <= 0.05187319884726225": [{"orf_len <= -0.8939773101058563": ["non_ess", {"orf_len <= -0.8857973935414988": ["ess", {"orf_len <= -0.8612576438484258": ["non_ess", "ess"]}]}]}, "ess"]}, {"hits_count_pro <= 12": [{"reads_count <= -0.2597188998118999": ["non_ess", "ess"]}, "non_ess"]}]}, {"reads_count <= -0.018990921986935458": [{"reads_count <= -0.36123069768989696": [{"reads_count <= -0.36413103477212544": ["non_ess", "ess"]}, "non_ess"]}, {"reads_count <= 0.01581312299980639": [{"orf_len <= -0.6758462017229871": ["non_ess", "ess"]}, "non_ess"]}]}]}]}, {"HFI_normalized <= 845": ["non_ess", {"insertion_index <= 0.011910926980838944": ["non_ess", "ess"]}]}]}]}, {"insertion_index <= 0.0058762530245419975": [{"hits_count_pro <= 0": [{"orf_len <= -0.9157904209441432": ["non_ess", {"HFI_normalized <= 1247": [{"orf_len <= -0.6731195628682013": [{"orf_len <= -0.7794584782048499": [{"HFI_normalized <= 458": [{"insertion_index <= 0.0025510204081632647": [{"orf_len <= -0.8612576438484258": ["non_ess", "ess"]}, "ess"]}, "non_ess"]}, "ess"]}, {"reads_count <= -0.2104131694140156": [{"orf_len <= -0.6322199800464133": [{"reads_count <= -0.4424401359922946": ["ess", "non_ess"]}, {"orf_len <= -0.6131335080629122": ["ess", {"insertion_index <= 0.002051282051282052": [{"insertion_index <= 0.0010940919037199122": [{"orf_len <= -0.4240865474644256": [{"orf_len <= -0.6076802303533405": ["ess", "non_ess"]}, {"HFI_normalized <= 1223": [{"reads_count <= -0.4221377764166952": [{"orf_len <= 0.05216637250483885": [{"orf_len <= 0.043986455940481256": [{"HFI_normalized <= 442": ["ess", {"HFI_normalized <= 492": ["non_ess", {"NI <= 0.02100949488666508": ["ess", "non_ess"]}]}]}, "non_ess"]}, "ess"]}, "non_ess"]}, "non_ess"]}]}, {"insertion_index <= 0.0013123359580052493": ["non_ess", {"insertion_index <= 0.001784121320249777": [{"HFI_normalized <= 875": [{"orf_len <= 0.019446706247408473": ["ess", "non_ess"]}, "ess"]}, "non_ess"]}]}]}, {"orf_len <= -0.5804138418054818": ["non_ess", {"insertion_index <= 0.0049400141143260395": [{"insertion_index <= 0.0031466331025802393": [{"HFI_normalized <= 498": [{"HFI_normalized <= 320": ["ess", {"reads_count <= -0.4250381134989237": [{"reads_count <= -0.4453404730745231": ["non_ess", "ess"]}, "non_ess"]}]}, {"NI <= 0.06457504030589678": [{"NI <= 0.06308407593955832": ["ess", "non_ess"]}, "ess"]}]}, {"HFI_normalized <= 310": ["non_ess", {"NI <= 0.17721238938053094": [{"NI <= 0.13691785365172462": [{"hits_count <= -0.3824825244140385": [{"HFI_normalized <= 613": [{"HFI_normalized <= 517": ["ess", "non_ess"]}, "ess"]}, "non_ess"]}, "ess"]}, {"NI <= 0.2561166971003189": ["non_ess", "ess"]}]}]}]}, "ess"]}]}]}]}]}, {"NI <= 0.16183451975754462": ["non_ess", {"hits_count <= -0.15102695753593598": ["non_ess", "ess"]}]}]}]}, "ess"]}]}, {"insertion_index <= 0.0028943560057887122": [{"orf_len <= -0.8721641992675694": ["ess", {"orf_len <= -0.2423106238120345": [{"orf_len <= -0.5095212315810493": [{"orf_len <= -0.5749605640959101": [{"insertion_index <= 0.0016611295681063125": [{"hits_count_pro <= 3": ["non_ess", "ess"]}, "ess"]}, "ess"]}, "non_ess"]}, {"HFI_normalized <= 334": ["non_ess", "ess"]}]}]}, {"HFI_normalized <= 1057": [{"reads_count <= -0.3583303606076685": [{"reads_count <= -0.3786327201832679": ["non_ess", {"NI <= 0.1871450696954053": ["ess", "non_ess"]}]}, "non_ess"]}, {"reads_count <= -0.3061242931275557": ["ess", "non_ess"]}]}]}]}, {"hits_count <= 0.08042860934216649": [{"HFI_normalized <= 315": [{"hits_count_pro <= 2": [{"orf_len <= -0.3513761780034692": [{"insertion_index <= 0.048701298701298704": [{"hits_count <= -0.3824825244140385": [{"HFI_normalized <= 135": ["non_ess", {"HFI_normalized <= 162": [{"NI <= 0.32095466323345645": [{"orf_len <= -0.8558043661388542": ["non_ess", {"insertion_index <= 0.00667779632721202": ["non_ess", "ess"]}]}, "ess"]}, {"insertion_index <= 0.009836065573770493": [{"insertion_index <= 0.00974025974025974": [{"HFI_normalized <= 256": ["non_ess", {"NI <= 0.18273034803050284": ["ess", {"HFI_normalized <= 265": ["ess", {"NI <= 0.3948071577015465": ["non_ess", "ess"]}]}]}]}, "ess"]}, "non_ess"]}]}]}, {"insertion_index <= 0.03934426229508197": ["non_ess", {"insertion_index <= 0.0410958904109589": ["ess", "non_ess"]}]}]}, "ess"]}, "non_ess"]}, {"hits_count_pro <= 10": [{"insertion_index <= 0.008342022940563087": [{"insertion_index <= 0.007949125596184421": ["non_ess", "ess"]}, "non_ess"]}, {"NI <= 0.2220991520892216": ["ess", {"HFI_normalized <= 85": ["ess", "non_ess"]}]}]}]}, {"hits_count_pro <= 0": [{"insertion_index <= 0.013832384052074858": [{"HFI_normalized <= 700": [{"insertion_index <= 0.007186858316221766": [{"insertion_index <= 0.006739679865206402": [{"NI <= 0.10993811561324413": ["ess", {"reads_count <= -0.10600103445379007": ["non_ess", "ess"]}]}, "ess"]}, {"orf_len <= -0.7876383947692076": ["ess", "non_ess"]}]}, "ess"]}, {"NI <= 0.720548989706443": ["ess", "non_ess"]}]}, {"HFI_normalized <= 512": [{"NI <= 0.14972620599739245": [{"reads_count <= -0.3235263156209266": ["ess", "non_ess"]}, "non_ess"]}, {"NI <= 0.2150995285489785": [{"HFI_normalized <= 541": ["ess", "non_ess"]}, {"HFI_normalized <= 547": ["non_ess", "ess"]}]}]}]}]}, {"orf_len <= -0.8967039489606422": [{"HFI_normalized <= 138": ["non_ess", "ess"]}, {"HFI_normalized <= 845": ["non_ess", {"insertion_index <= 0.012156448202959831": ["non_ess", "ess"]}]}]}]}]}, {"insertion_index <= 0.005912495072920773": [{"hits_count_pro <= 0": [{"HFI_normalized <= 408": [{"hits_count <= -0.4403464161335641": [{"orf_len <= -0.9266969763632869": ["non_ess", {"HFI_normalized <= 396": [{"reads_count <= -0.43083878766338063": [{"HFI_normalized <= 155": ["non_ess", "ess"]}, {"NI <= 0.07850005937335662": ["non_ess", {"orf_len <= -0.11415859763709893": [{"HFI_normalized <= 377": [{"insertion_index <= 0.004464285714285714": ["non_ess", {"NI <= 0.10620322919570298": ["non_ess", {"NI <= 0.1782476826608506": ["ess", "non_ess"]}]}]}, "ess"]}, "ess"]}]}]}, "non_ess"]}]}, "non_ess"]}, {"hits_count <= 0.022564717622640867": [{"HFI_normalized <= 1376": [{"HFI_normalized <= 444": [{"reads_count <= -0.4395397989100661": ["non_ess", "ess"]}, {"HFI_normalized <= 454": [{"orf_len <= -0.6976593125612739": ["ess", "non_ess"]}, {"NI <= 0.11246878576630943": [{"insertion_index <= 0.003473428273706148": [{"reads_count <= -0.2800212593874993": [{"reads_count <= -0.3728320460188109": [{"reads_count <= -0.4047357539233243": [{"NI <= 0.025245947444084416": [{"NI <= 0.021846425841858585": [{"HFI_normalized <= 1241": [{"HFI_normalized <= 616": [{"orf_len <= -0.6076802303533405": [{"orf_len <= -0.7794584782048499": ["non_ess", "ess"]}, "non_ess"]}, "ess"]}, "non_ess"]}, "non_ess"]}, {"insertion_index <= 0.0023023791250959325": ["ess", {"orf_len <= -0.16051145816845866": ["non_ess", "ess"]}]}]}, {"orf_len <= 0.1039725107457703": ["ess", {"reads_count <= -0.3844333943477248": ["non_ess", "ess"]}]}]}, "ess"]}, "non_ess"]}, "ess"]}, {"NI <= 0.11631089217296114": ["non_ess", {"HFI_normalized <= 657": [{"orf_len <= 0.4775220338514338": [{"NI <= 0.1895181709859994": ["ess", "non_ess"]}, "non_ess"]}, "ess"]}]}]}]}]}, {"HFI_normalized <= 1634": ["ess", {"HFI_normalized <= 1638": ["non_ess", "ess"]}]}]}, {"HFI_normalized <= 728": [{"hits_count <= 0.1382925010616921": ["non_ess", "ess"]}, "non_ess"]}]}]}, {"orf_len <= -0.7821851170596359": ["non_ess", {"insertion_index <= 0.0033287101248266303": [{"hits_count <= -0.7296658747311922": [{"insertion_index <= 0.0007052186177715093": [{"orf_len <= -0.5749605640959101": ["non_ess", "ess"]}, {"reads_count <= -0.4250381134989237": ["non_ess", {"hits_count_pro <= 1": ["non_ess", "ess"]}]}]}, {"NI <= 0.18377628348809905": ["ess", "non_ess"]}]}, {"hits_count <= 0.022564717622640867": [{"hits_count <= -0.5560741995726153": [{"insertion_index <= 0.004860267314702308": [{"insertion_index <= 0.0038572806171648993": ["non_ess", {"hits_count_pro <= 1": ["ess", {"orf_len <= -0.7467388119474196": ["ess", {"NI <= 0.08452678755273614": ["ess", {"insertion_index <= 0.003989361702127659": ["ess", "non_ess"]}]}]}]}]}, {"NI <= 0.2038785989363653": ["non_ess", "ess"]}]}, "non_ess"]}, {"hits_count <= 0.1961563927812177": ["ess", "non_ess"]}]}]}]}]}, {"insertion_index <= 0.010121457489878544": [{"orf_len <= 1.0283030825181785": [{"insertion_index <= 0.010026155187445507": [{"hits_count_pro <= 3": [{"hits_count <= -0.09316306581641036": [{"insertion_index <= 0.006261180679785331": ["non_ess", {"HFI_normalized <= 464": [{"reads_count <= -0.2655195739763569": [{"hits_count <= -0.2667547409749872": [{"orf_len <= -0.06235245939616747": [{"orf_len <= -0.2177708741189618": [{"NI <= 0.17819823162060225": ["non_ess", {"orf_len <= -0.940330170637216": ["ess", {"hits_count <= -0.6718019830116665": [{"reads_count <= -0.4424401359922946": ["ess", "non_ess"]}, {"hits_count <= -0.3824825244140385": [{"NI <= 0.2866600269494405": [{"hits_count <= -0.4403464161335641": ["non_ess", "ess"]}, {"orf_len <= -0.7194724233995609": ["non_ess", "ess"]}]}, "non_ess"]}]}]}]}, "non_ess"]}, "ess"]}, "non_ess"]}, "non_ess"]}, {"NI <= 0.19039301310043666": [{"hits_count_pro <= 1": ["ess", "non_ess"]}, {"insertion_index <= 0.006497022198159177": ["non_ess", {"orf_len <= 0.13941881585798654": [{"insertion_index <= 0.009551800146950772": [{"HFI_normalized <= 518": ["ess", "non_ess"]}, "ess"]}, "ess"]}]}]}]}]}, "non_ess"]}, "non_ess"]}, "ess"]}, "non_ess"]}, {"orf_len <= -0.7630986450761348": [{"HFI_normalized <= 115": [{"orf_len <= -0.9594166426207172": [{"orf_len <= -1.0139494197164345": ["non_ess", "ess"]}, "non_ess"]}, {"HFI_normalized <= 119": ["ess", {"orf_len <= -0.8612576438484258": ["non_ess", {"hits_count_pro <= 2": [{"HFI_normalized <= 145": ["non_ess", {"NI <= 0.3989428609661448": ["non_ess", "ess"]}]}, "non_ess"]}]}]}]}, {"HFI_normalized <= 760": [{"hits_count_pro <= 1": [{"insertion_index <= 0.012178619756427604": [{"insertion_index <= 0.012173913043478259": ["non_ess", "ess"]}, "non_ess"]}, "non_ess"]}, {"orf_len <= 0.47479539499664797": ["ess", {"HFI_normalized <= 968": ["non_ess", "ess"]}]}]}]}]}]}, {"insertion_index <= 0.005010737294201861": [{"hits_count_pro <= 0": [{"HFI_normalized <= 1247": [{"HFI_normalized <= 128": ["non_ess", {"hits_count <= -0.4403464161335641": [{"orf_len <= 0.22394462035634835": [{"orf_len <= 0.1884983152441321": [{"HFI_normalized <= 222": ["ess", {"HFI_normalized <= 238": ["non_ess", {"orf_len <= -0.8885240323962846": ["non_ess", {"NI <= 0.17721238938053094": [{"NI <= 0.13691785365172462": [{"HFI_normalized <= 1223": [{"NI <= 0.10709873690048996": [{"HFI_normalized <= 321": ["ess", {"HFI_normalized <= 332": ["non_ess", "ess"]}]}, {"reads_count <= -0.3815330572654964": ["non_ess", "ess"]}]}, "non_ess"]}, "ess"]}, {"insertion_index <= 0.0039164490861618795": ["ess", "non_ess"]}]}]}]}]}, "non_ess"]}, {"HFI_normalized <= 701": [{"NI <= 0.07717357593300941": ["non_ess", {"reads_count <= -0.4250381134989237": ["non_ess", "ess"]}]}, "ess"]}]}, {"HFI_normalized <= 883": [{"HFI_normalized <= 657": [{"reads_count <= -0.24811755148298595": ["ess", "non_ess"]}, "ess"]}, {"orf_len <= 1.9390004600166573": ["non_ess", "ess"]}]}]}]}, "ess"]}, {"NI <= 0.09010957342171044": [{"orf_len <= 0.09851923303619856": [{"insertion_index <= 0.004520795660036167": [{"reads_count <= -0.4250381134989237": [{"reads_count <= -0.4453404730745231": [{"orf_len <= -0.6703929240134154": [{"orf_len <= -0.8558043661388542": [{"orf_len <= -0.8721641992675694": [{"HFI_normalized <= 353": [{"orf_len <= -0.8967039489606422": ["non_ess", "ess"]}, "ess"]}, "non_ess"]}, "ess"]}, "non_ess"]}, {"insertion_index <= 0.001314060446780552": ["non_ess", "ess"]}]}, "non_ess"]}, "ess"]}, {"insertion_index <= 0.004414261460101867": [{"hits_count_pro <= 2": [{"HFI_normalized <= 306": ["non_ess", "ess"]}, {"hits_count <= -0.5560741995726153": ["non_ess", "ess"]}]}, "non_ess"]}]}, {"NI <= 0.2456868131868132": [{"HFI_normalized <= 395": [{"HFI_normalized <= 391": ["non_ess", "ess"]}, "non_ess"]}, "ess"]}]}]}, {"hits_count_pro <= 0": [{"insertion_index <= 0.013953488372093023": [{"insertion_index <= 0.0067720090293453715": [{"reads_count <= -0.1031006973715616": [{"orf_len <= 0.7420060027656628": [{"insertion_index <= 0.006369426751592357": [{"reads_count <= -0.2829215964697278": [{"hits_count <= -0.4403464161335641": [{"hits_count <= -0.5560741995726153": [{"orf_len <= -0.5722339252411243": [{"orf_len <= -0.6376732577559849": [{"orf_len <= -0.9212436986537148": ["non_ess", {"NI <= 0.20474013138190605": ["ess", "non_ess"]}]}, "non_ess"]}, "ess"]}, "non_ess"]}, "ess"]}, "non_ess"]}, "ess"]}, "non_ess"]}, "ess"]}, {"hits_count <= 0.1382925010616921": [{"HFI_normalized <= 670": [{"reads_count <= -0.3699317089365824": [{"NI <= 0.3203586042399194": [{"hits_count <= -0.5560741995726153": [{"NI <= 0.22109109601287324": [{"orf_len <= -0.7085658679804175": [{"reads_count <= -0.4337391247456092": [{"insertion_index <= 0.008620689655172414": ["non_ess", "ess"]}, "non_ess"]}, "ess"]}, "non_ess"]}, {"NI <= 0.20825616762419727": ["non_ess", "ess"]}]}, "ess"]}, {"reads_count <= -0.09439968612487612": [{"reads_count <= -0.33512766394984056": [{"reads_count <= -0.33802800103206904": ["non_ess", "ess"]}, "non_ess"]}, {"hits_count <= -0.15102695753593598": [{"insertion_index <= 0.00696594427244582": ["non_ess", "ess"]}, "non_ess"]}]}]}, {"NI <= 0.2469983396988225": ["ess", "non_ess"]}]}, "non_ess"]}]}, "non_ess"]}, {"HFI_normalized <= 1516": [{"hits_count <= 0.1382925010616921": [{"reads_count <= -0.04219361864476336": [{"insertion_index <= 0.02531645569620253": [{"reads_count <= -0.4134367651700097": [{"orf_len <= -0.6158601469176981": ["non_ess", "ess"]}, {"NI <= 0.1965954512843925": [{"NI <= 0.1950924406336872": ["non_ess", "ess"]}, "non_ess"]}]}, {"insertion_index <= 0.025936599423631124": ["ess", "non_ess"]}]}, {"reads_count <= 0.01581312299980639": [{"HFI_normalized <= 218": ["non_ess", {"hits_count_pro <= 4": [{"insertion_index <= 0.005202312138728325": ["non_ess", "ess"]}, "non_ess"]}]}, "non_ess"]}]}, "non_ess"]}, {"hits_count <= 0.5433397430983714": ["ess", "non_ess"]}]}]}]}, {"insertion_index <= 0.0067720090293453715": [{"hits_count_pro <= 0": [{"insertion_index <= 0.0030349013657056147": [{"orf_len <= 1.0746559430495384": [{"insertion_index <= 0.002652519893899204": [{"HFI_normalized <= 311": [{"HFI_normalized <= 229": [{"HFI_normalized <= 126": [{"HFI_normalized <= 94": ["non_ess", "ess"]}, "ess"]}, "non_ess"]}, {"HFI_normalized <= 388": ["ess", {"orf_len <= 0.9328707226006732": [{"HFI_normalized <= 1247": [{"hits_count <= -0.7296658747311922": [{"HFI_normalized <= 1241": [{"HFI_normalized <= 536": [{"insertion_index <= 0.0020222446916076846": [{"HFI_normalized <= 469": ["ess", {"orf_len <= -0.6158601469176981": ["ess", {"insertion_index <= 0.0013123359580052493": ["non_ess", "ess"]}]}]}, "non_ess"]}, {"orf_len <= 0.2893839528712091": [{"orf_len <= -0.3077499563268953": [{"orf_len <= -0.3213831506008247": ["ess", "non_ess"]}, "ess"]}, {"insertion_index <= 0.0005458515283842794": ["ess", "non_ess"]}]}]}, "non_ess"]}, "ess"]}, "ess"]}, "non_ess"]}]}]}, "ess"]}, "ess"]}, {"orf_len <= -0.8694375604127835": ["non_ess", {"reads_count <= -0.4163371022522382": ["ess", {"insertion_index <= 0.006616257088846882": [{"reads_count <= -0.3061242931275557": [{"NI <= 0.09433345529942676": ["ess", {"NI <= 0.32487090292331955": [{"insertion_index <= 0.006015037593984964": [{"insertion_index <= 0.0050536955148452285": [{"insertion_index <= 0.004491017964071856": [{"orf_len <= -0.6104068692081264": ["non_ess", {"orf_len <= -0.14142498618495758": ["ess", {"HFI_normalized <= 339": ["ess", {"HFI_normalized <= 686": [{"insertion_index <= 0.0041597337770382685": ["non_ess", "ess"]}, {"reads_count <= -0.3815330572654964": [{"NI <= 0.1125376439698345": ["non_ess", "ess"]}, "ess"]}]}]}]}]}, {"NI <= 0.19552280798611296": [{"hits_count <= -0.3824825244140385": ["ess", "non_ess"]}, "non_ess"]}]}, "non_ess"]}, "ess"]}, "non_ess"]}]}, {"hits_count <= 0.1961563927812177": [{"orf_len <= 1.3364132731089813": [{"reads_count <= 0.007112111753120929": [{"insertion_index <= 0.005694760820045559": [{"NI <= 0.20257614678899089": [{"hits_count <= -0.6139380912921409": ["ess", {"reads_count <= -0.1031006973715616": [{"insertion_index <= 0.003202846975088968": ["ess", "non_ess"]}, "ess"]}]}, "ess"]}, "non_ess"]}, "ess"]}, "non_ess"]}, "ess"]}]}, "ess"]}]}]}]}, {"HFI_normalized <= 652": [{"hits_count <= -0.6139380912921409": [{"orf_len <= -0.19050448557110314": [{"orf_len <= -0.3977290385348289": [{"hits_count_pro <= 3": [{"insertion_index <= 0.0038022813688212928": [{"reads_count <= -0.4482408101567516": [{"reads_count <= -0.4511411472389801": [{"HFI_normalized <= 554": [{"orf_len <= -0.8721641992675694": ["ess", "non_ess"]}, "ess"]}, "ess"]}, "non_ess"]}, {"HFI_normalized <= 278": [{"HFI_normalized <= 214": ["non_ess", "ess"]}, {"NI <= 0.08699088205948888": ["ess", {"hits_count_pro <= 2": ["non_ess", "ess"]}]}]}]}, "non_ess"]}, "non_ess"]}, {"HFI_normalized <= 306": ["non_ess", "ess"]}]}, {"reads_count <= -0.4134367651700097": ["ess", {"orf_len <= 1.1400952755643992": ["non_ess", {"orf_len <= 1.603623880877996": ["ess", "non_ess"]}]}]}]}, {"insertion_index <= 0.0036719706242350062": [{"hits_count_pro <= 3": [{"orf_len <= 0.19395159295370384": [{"reads_count <= -0.4453404730745231": ["ess", {"HFI_normalized <= 694": ["ess", "non_ess"]}]}, "ess"]}, "non_ess"]}, {"HFI_normalized <= 934": [{"NI <= 0.10650393736118276": ["ess", {"NI <= 0.18005692296130435": ["non_ess", "ess"]}]}, "non_ess"]}]}]}]}, {"hits_count <= 0.08042860934216649": [{"hits_count_pro <= 0": [{"reads_count <= -0.24811755148298595": [{"orf_len <= -0.7258345807273947": [{"NI <= 1.2120995646835584": ["non_ess", "ess"]}, {"reads_count <= -0.2626192368941284": [{"NI <= 0.1772080547348779": ["ess", {"reads_count <= -0.3206259785386981": [{"NI <= 0.32966577935522035": [{"NI <= 0.2597330595482546": [{"hits_count <= -0.4982103078530897": ["ess", {"insertion_index <= 0.007782101167315175": ["non_ess", "ess"]}]}, "non_ess"]}, "ess"]}, "non_ess"]}]}, "ess"]}]}, {"reads_count <= -0.018990921986935458": ["non_ess", {"reads_count <= 0.004211774670892442": ["ess", "non_ess"]}]}]}, {"orf_len <= -0.8857973935414988": [{"orf_len <= -0.9103371432345716": [{"NI <= 0.30140510918416785": [{"HFI_normalized <= 132": ["ess", {"NI <= 0.19460403289399567": ["ess", "non_ess"]}]}, {"hits_count <= -0.2667547409749872": ["non_ess", {"reads_count <= 0.3174481795515691": [{"NI <= 0.8132080685272174": ["ess", "non_ess"]}, "ess"]}]}]}, {"HFI_normalized <= 119": ["ess", {"hits_count_pro <= 2": ["ess", "non_ess"]}]}]}, {"NI <= 0.2255553496253541": [{"NI <= 0.225535291896848": [{"hits_count_pro <= 2": [{"reads_count <= -0.2539182256474429": ["non_ess", {"hits_count <= -0.15102695753593598": [{"reads_count <= -0.1698084502628168": [{"HFI_normalized <= 129": ["non_ess", "ess"]}, "non_ess"]}, "non_ess"]}]}, "non_ess"]}, "ess"]}, {"reads_count <= -0.35543002352543995": [{"orf_len <= -0.7849117559144217": [{"hits_count_pro <= 1": ["ess", {"reads_count <= -0.36123069768989696": ["non_ess", "ess"]}]}, "non_ess"]}, {"reads_count <= -0.021891259069163945": ["non_ess", {"reads_count <= -0.0044892365757930215": ["ess", "non_ess"]}]}]}]}]}]}, "non_ess"]}]}]