[{"insertion_index <= 0.005565862708719851": [{"hits_count_pro <= 0": [{"HFI_normalized <= 1309": [{"hits_count <= 0.08042860934216649": [{"HFI_normalized <= 236": [{"HFI_normalized <= 222": [{"HFI_normalized <= 208": ["non_ess", "ess"]}, "non_ess"]}, {"reads_count <= -0.3206259785386981": [{"NI <= 0.10470102128323068": ["ess", "non_ess"]}, {"HFI_normalized <= 1177": ["ess", "non_ess"]}]}]}, "non_ess"]}, "ess"]}, {"insertion_index <= 0.004044489383215368": [{"hits_count_pro <= 3": [{"orf_len <= -0.09507212565359786": [{"reads_count <= -0.4076360910055528": [{"NI <= 0.0197093023255814": ["ess", "non_ess"]}, "ess"]}, {"HFI_normalized <= 1170": [{"orf_len <= 1.6908763242311438": ["ess", "non_ess"]}, "non_ess"]}]}, "non_ess"]}, {"hits_count_pro <= 1": [{"insertion_index <= 0.004633204633204633": ["ess", "non_ess"]}, "non_ess"]}]}]}, {"HFI_normalized <= 517": [{"hits_count_pro <= 2": [{"hits_count <= -0.4982103078530897": [{"orf_len <= -0.7194724233995609": [{"insertion_index <= 0.01694915254237288": ["non_ess", {"HFI_normalized <= 120": ["non_ess", "ess"]}]}, {"reads_count <= -0.4134367651700097": ["ess", {"NI <= 0.1772080547348779": ["ess", "non_ess"]}]}]}, {"insertion_index <= 0.09090909090909093": ["non_ess", "ess"]}]}, "non_ess"]}, {"hits_count_pro <= 1": [{"orf_len <= 1.0283030825181785": [{"HFI_normalized <= 686": [{"reads_count <= -0.31772564145646964": ["ess", {"NI <= 0.17988978194401214": ["ess", "non_ess"]}]}, "ess"]}, {"hits_count <= 0.311884176220269": [{"orf_len <= 1.2518874686106196": ["non_ess", {"reads_count <= -0.13500440527607493": ["non_ess", "ess"]}]}, "non_ess"]}]}, "non_ess"]}]}]}, {"insertion_index <= 0.006970509383378016": [{"hits_count_pro <= 0": [{"HFI_normalized <= 1432": [{"orf_len <= -0.839444533010139": [{"NI <= 0.0": [{"orf_len <= -0.9430568094920021": ["ess", {"HFI_normalized <= 314": ["non_ess", "ess"]}]}, "non_ess"]}, {"orf_len <= 1.3554997450924824": [{"hits_count <= -0.7296658747311922": [{"insertion_index <= 0.0014695077149155034": ["ess", "non_ess"]}, "ess"]}, {"HFI_normalized <= 636": ["non_ess", {"HFI_normalized <= 752": ["ess", "non_ess"]}]}]}]}, {"insertion_index <= 0.002281616688396349": ["ess", {"NI <= 0.04936549499159172": ["non_ess", "ess"]}]}]}, {"NI <= 0.059342962970664034": [{"insertion_index <= 0.0011627906976744186": [{"orf_len <= -0.5749605640959101": [{"HFI_normalized <= 443": [{"hits_count_pro <= 5": ["ess", "non_ess"]}, "non_ess"]}, "ess"]}, {"NI <= 0.03336519064231022": ["non_ess", {"HFI_normalized <= 892": [{"HFI_normalized <= 512": ["ess", "non_ess"]}, "ess"]}]}]}, {"hits_count_pro <= 2": [{"HFI_normalized <= 897": ["non_ess", {"NI <= 0.1578812468642977": ["ess", {"insertion_index <= 0.0060557125555107": ["non_ess", "ess"]}]}]}, "non_ess"]}]}]}, {"hits_count <= 0.1382925010616921": [{"NI <= 0.40564678345463184": [{"hits_count_pro <= 0": [{"NI <= 0.1858207767402377": ["ess", {"reads_count <= -0.33512766394984056": [{"orf_len <= -0.7985449501883509": ["non_ess", "ess"]}, {"orf_len <= -0.9266969763632869": ["ess", "non_ess"]}]}]}, {"NI <= 0.405440414507772": [{"orf_len <= -0.5804138418054818": ["non_ess", {"orf_len <= -0.5504208144028373": ["ess", "non_ess"]}]}, "ess"]}]}, {"hits_count_pro <= 11": [{"reads_count <= -0.35543002352543995": [{"insertion_index <= 0.01324503311258278": ["non_ess", {"NI <= 0.4971518987341772": ["ess", "non_ess"]}]}, "non_ess"]}, {"insertion_index <= 0.03503184713375796": ["non_ess", "ess"]}]}]}, {"reads_count <= 3.5658257116474754": ["non_ess", {"HFI_normalized <= 88": ["non_ess", "ess"]}]}]}]}, {"insertion_index <= 0.005639760310186817": [{"insertion_index <= 0.002325581395348837": [{"orf_len <= -0.8830707546867129": ["non_ess", {"HFI_normalized <= 975": [{"NI <= 0.08864760157006676": [{"hits_count_pro <= 0": [{"HFI_normalized <= 954": ["ess", "non_ess"]}, {"reads_count <= -0.4250381134989237": ["ess", "non_ess"]}]}, "non_ess"]}, {"reads_count <= -0.3061242931275557": ["ess", "non_ess"]}]}]}, {"hits_count_pro <= 0": [{"NI <= 0.06828483373407025": ["non_ess", {"HFI_normalized <= 1228": [{"insertion_index <= 0.003076923076923077": [{"HFI_normalized <= 642": ["ess", "non_ess"]}, {"HFI_normalized <= 232": ["non_ess", "ess"]}]}, "ess"]}]}, {"HFI_normalized <= 314": ["non_ess", {"NI <= 0.10756257678609102": [{"insertion_index <= 0.004594180704441043": [{"NI <= 0.043038918142138616": ["ess", "non_ess"]}, "ess"]}, {"NI <= 0.14712524334847502": [{"insertion_index <= 0.004364089775561097": ["ess", "non_ess"]}, {"reads_count <= -0.4250381134989237": ["ess", "non_ess"]}]}]}]}]}]}, {"insertion_index <= 0.00997506234413965": [{"hits_count_pro <= 0": [{"reads_count <= -0.36123069768989696": [{"NI <= 0.13104304072890466": ["non_ess", {"NI <= 0.1782476826608506": [{"reads_count <= -0.4424401359922946": ["non_ess", "ess"]}, {"NI <= 0.2846299810246679": ["non_ess", "ess"]}]}]}, {"HFI_normalized <= 203": ["non_ess", {"reads_count <= -0.33512766394984056": ["ess", "non_ess"]}]}]}, "non_ess"]}, {"reads_count <= -0.31772564145646964": [{"reads_count <= -0.4134367651700097": ["ess", {"reads_count <= -0.3206259785386981": [{"hits_count_pro <= 0": [{"orf_len <= -0.7385588953830621": ["non_ess", "ess"]}, "non_ess"]}, "ess"]}]}, "non_ess"]}]}]}, {"hits_count_pro <= 0": [{"insertion_index <= 0.005329593267882188": [{"HFI_normalized <= 1376": [{"HFI_normalized <= 1196": [{"HFI_normalized <= 191": ["non_ess", {"orf_len <= 2.298916788848392": ["ess", "non_ess"]}]}, {"NI <= 0.09785762646290744": ["non_ess", "ess"]}]}, "ess"]}, {"hits_count <= 0.08042860934216649": [{"NI <= 0.28442262981141825": [{"insertion_index <= 0.01160541586073501": [{"reads_count <= -0.36123069768989696": [{"insertion_index <= 0.008108108108108109": ["non_ess", "ess"]}, "non_ess"]}, "ess"]}, {"reads_count <= -0.3815330572654964": ["ess", {"HFI_normalized <= 307": ["non_ess", {"NI <= 0.4054406566699564": ["non_ess", "ess"]}]}]}]}, "non_ess"]}]}, {"NI <= 0.2517376569871752": [{"hits_count_pro <= 2": [{"reads_count <= -0.19011080983841624": [{"HFI_normalized <= 970": [{"HFI_normalized <= 198": ["non_ess", {"reads_count <= -0.1959114840028732": ["non_ess", "ess"]}]}, {"hits_count <= -0.7875297664507178": [{"insertion_index <= 0.0009345794392523364": ["ess", "non_ess"]}, "ess"]}]}, "non_ess"]}, {"orf_len <= -0.3213831506008247": [{"HFI_normalized <= 365": [{"orf_len <= -0.9321502540728585": ["ess", "non_ess"]}, {"NI <= 0.140464771708192": [{"hits_count_pro <= 4": ["ess", "non_ess"]}, "ess"]}]}, "non_ess"]}]}, {"orf_len <= -0.4304487047922593": [{"orf_len <= -0.4386286213566168": [{"reads_count <= 3.577427059976389": [{"reads_count <= -0.4337391247456092": [{"insertion_index <= 0.0125": ["non_ess", "ess"]}, "non_ess"]}, {"HFI_normalized <= 65": ["non_ess", "ess"]}]}, "ess"]}, "non_ess"]}]}]}, {"NI <= 0.19039301310043666": [{"hits_count_pro <= 0": [{"insertion_index <= 0.0058762530245419975": [{"NI <= 0.10157593527106652": [{"insertion_index <= 0.0018326206475259624": [{"reads_count <= -0.4018354168410958": ["ess", {"orf_len <= 0.9737703054224612": ["non_ess", "ess"]}]}, "ess"]}, {"NI <= 0.10794200323807028": ["non_ess", {"HFI_normalized <= 328": [{"hits_count <= -0.8453936581702434": ["non_ess", "ess"]}, {"HFI_normalized <= 537": ["non_ess", "ess"]}]}]}]}, {"HFI_normalized <= 379": [{"reads_count <= -0.4134367651700097": ["non_ess", {"hits_count <= -0.32461863269451285": ["ess", "non_ess"]}]}, "non_ess"]}]}, {"insertion_index <= 0.004056795131845843": [{"orf_len <= -0.22867742953810524": [{"NI <= 0.12329482057373213": [{"insertion_index <= 0.003846153846153847": ["non_ess", "ess"]}, "ess"]}, {"reads_count <= -0.4221377764166952": ["ess", {"HFI_normalized <= 418": ["ess", {"hits_count_pro <= 1": ["ess", "non_ess"]}]}]}]}, {"NI <= 0.18062040589894127": ["non_ess", {"hits_count <= -0.7875297664507178": ["ess", "non_ess"]}]}]}]}, {"insertion_index <= 0.009308510638297872": [{"hits_count_pro <= 0": [{"NI <= 0.3994432557076677": [{"HFI_normalized <= 200": ["non_ess", {"hits_count <= -0.4403464161335641": [{"NI <= 0.20257614678899089": ["non_ess", "ess"]}, {"HFI_normalized <= 1132": ["non_ess", "ess"]}]}]}, "ess"]}, {"reads_count <= -0.2568185627296714": [{"HFI_normalized <= 638": ["non_ess", "ess"]}, "non_ess"]}]}, {"reads_count <= -0.4337391247456092": [{"insertion_index <= 0.012987012987012988": ["non_ess", "ess"]}, {"HFI_normalized <= 258": ["non_ess", {"HFI_normalized <= 259": ["ess", "non_ess"]}]}]}]}]}, {"insertion_index <= 0.005487804878048779": [{"hits_count_pro <= 2": [{"HFI_normalized <= 723": [{"reads_count <= -0.3003236189630987": [{"HFI_normalized <= 322": [{"reads_count <= -0.42793845058115215": [{"NI <= 0.14296159408645348": ["non_ess", "ess"]}, "non_ess"]}, {"orf_len <= 0.03853317823090953": [{"reads_count <= -0.4221377764166952": ["ess", "non_ess"]}, "ess"]}]}, "non_ess"]}, {"insertion_index <= 0.0016168148746968473": ["ess", {"orf_len <= 2.427068815023328": [{"orf_len <= 1.0746559430495384": [{"hits_count <= -0.6139380912921409": ["ess", "non_ess"]}, "ess"]}, {"orf_len <= 3.2777801377165168": ["non_ess", "ess"]}]}]}]}, {"insertion_index <= 0.0": ["ess", "non_ess"]}]}, {"hits_count_pro <= 0": [{"reads_count <= -0.3293269897853836": [{"orf_len <= -0.940330170637216": ["ess", {"insertion_index <= 0.006153846153846154": ["non_ess", {"HFI_normalized <= 223": ["non_ess", {"hits_count <= -0.7296658747311922": ["non_ess", "ess"]}]}]}]}, {"NI <= 0.12820330296127566": ["ess", {"HFI_normalized <= 409": [{"orf_len <= -0.4113622328087582": [{"orf_len <= -0.4604417321949038": ["non_ess", "ess"]}, "non_ess"]}, {"orf_len <= 1.0555694710660373": [{"orf_len <= 0.9710436665676754": ["non_ess", "ess"]}, "non_ess"]}]}]}]}, {"hits_count <= -0.15102695753593598": [{"insertion_index <= 0.03571428571428571": [{"insertion_index <= 0.008813559322033898": [{"insertion_index <= 0.008720930232558141": [{"HFI_normalized <= 999": ["non_ess", "ess"]}, "ess"]}, {"reads_count <= -0.3902340685121817": [{"reads_count <= -0.3989350797588673": ["non_ess", "ess"]}, "non_ess"]}]}, {"hits_count <= -0.2667547409749872": ["non_ess", "ess"]}]}, {"hits_count_pro <= 1": [{"hits_count <= 0.1382925010616921": [{"hits_count <= 0.08042860934216649": ["non_ess", {"NI <= 0.3708785402282655": ["non_ess", "ess"]}]}, "non_ess"]}, "non_ess"]}]}]}]}, {"insertion_index <= 0.006970509383378016": [{"insertion_index <= 0.0043699927166788045": [{"HFI_normalized <= 215": ["non_ess", {"orf_len <= -0.8176314221718521": [{"hits_count <= -0.9032575498897693": [{"orf_len <= -0.981229753459004": ["ess", {"hits_count_pro <= 1": ["non_ess", "ess"]}]}, "non_ess"]}, {"hits_count_pro <= 3": [{"HFI_normalized <= 1638": [{"reads_count <= -0.2829215964697278": ["ess", "non_ess"]}, "ess"]}, {"insertion_index <= 0.0": ["ess", "non_ess"]}]}]}]}, {"hits_count_pro <= 2": [{"orf_len <= 0.9410506391650308": [{"orf_len <= -0.045992626267452284": [{"orf_len <= -0.16051145816845866": [{"hits_count <= -0.5560741995726153": ["non_ess", "ess"]}, "non_ess"]}, {"reads_count <= -0.2278151919073865": ["ess", {"HFI_normalized <= 1095": ["non_ess", "ess"]}]}]}, {"insertion_index <= 0.005639760310186817": [{"insertion_index <= 0.005458956732713303": ["non_ess", "ess"]}, "non_ess"]}]}, "non_ess"]}]}, {"hits_count_pro <= 2": [{"NI <= 0.2239193841040512": [{"orf_len <= 0.4066294236270013": [{"insertion_index <= 0.0071428571428571435": ["non_ess", {"insertion_index <= 0.007434944237918215": ["ess", "non_ess"]}]}, "non_ess"]}, {"HFI_normalized <= 675": [{"hits_count <= -0.4982103078530897": [{"HFI_normalized <= 226": ["non_ess", {"HFI_normalized <= 265": ["ess", "non_ess"]}]}, {"NI <= 1.5017862910724598": ["non_ess", {"hits_count_pro <= 1": ["non_ess", "ess"]}]}]}, {"insertion_index <= 0.008480917934647045": ["non_ess", {"NI <= 0.4031159730115858": [{"orf_len <= 1.0283030825181785": ["ess", "non_ess"]}, "non_ess"]}]}]}]}, {"orf_len <= -0.9430568094920021": [{"orf_len <= -1.000316225442505": ["non_ess", "ess"]}, "non_ess"]}]}]}, {"insertion_index <= 0.00847457627118644": [{"insertion_index <= 0.004497751124437782": [{"NI <= 0.29131942129475297": [{"HFI_normalized <= 204": ["non_ess", {"HFI_normalized <= 1145": [{"orf_len <= 0.4093560624817872": [{"HFI_normalized <= 500": ["non_ess", "ess"]}, {"insertion_index <= 0.003969829297340214": ["non_ess", "ess"]}]}, {"orf_len <= 2.0589725696272354": ["ess", {"orf_len <= 3.245060471459087": ["non_ess", "ess"]}]}]}]}, "non_ess"]}, {"hits_count_pro <= 1": [{"HFI_normalized <= 1304": [{"hits_count <= 0.311884176220269": [{"HFI_normalized <= 472": ["non_ess", {"orf_len <= -0.33228970601996816": ["ess", "non_ess"]}]}, "non_ess"]}, "ess"]}, {"NI <= 0.2182803564303764": [{"HFI_normalized <= 545": ["non_ess", {"orf_len <= 0.6629334759768727": ["non_ess", "ess"]}]}, {"hits_count_pro <= 8": [{"NI <= 0.22237325236548508": ["ess", {"insertion_index <= 0.008008736803785948": ["non_ess", "ess"]}]}, "ess"]}]}]}]}, {"reads_count <= -0.3206259785386981": [{"insertion_index <= 0.00997506234413965": [{"NI <= 0.25058584948174856": ["non_ess", {"hits_count_pro <= 0": ["ess", {"reads_count <= -0.3235263156209266": ["non_ess", "ess"]}]}]}, {"reads_count <= -0.3902340685121817": [{"insertion_index <= 0.013100436681222708": ["non_ess", {"insertion_index <= 0.014234875444839857": ["ess", "non_ess"]}]}, "non_ess"]}]}, {"HFI_normalized <= 258": ["non_ess", {"hits_count <= -0.15102695753593598": [{"reads_count <= -0.016090584904706967": ["non_ess", "ess"]}, {"HFI_normalized <= 259": ["ess", {"HFI_normalized <= 845": ["non_ess", {"NI <= 0.3976361933060174": ["non_ess", "ess"]}]}]}]}]}]}]}, {"insertion_index <= 0.005994005994005994": [{"hits_count_pro <= 1": [{"insertion_index <= 0.003154574132492113": [{"HFI_normalized <= 517": [{"insertion_index <= 0.0026631158455392807": [{"NI <= 0.049471657602186116": [{"orf_len <= -0.9239703375085008": ["non_ess", "ess"]}, {"HFI_normalized <= 178": ["ess", "non_ess"]}]}, "ess"]}, {"hits_count <= -0.5560741995726153": ["ess", {"insertion_index <= 0.002712288754433549": [{"orf_len <= 3.245060471459087": ["non_ess", "ess"]}, "ess"]}]}]}, {"HFI_normalized <= 1304": [{"NI <= 0.20034740187744848": [{"reads_count <= -0.26841991105858537": [{"hits_count <= -0.4982103078530897": ["non_ess", "ess"]}, {"reads_count <= 0.08252087589106159": ["non_ess", "ess"]}]}, {"NI <= 0.2536410957463589": ["ess", {"NI <= 0.3236912813860836": ["non_ess", "ess"]}]}]}, "ess"]}]}, {"insertion_index <= 0.0007251631617113853": [{"orf_len <= -0.7985449501883509": [{"hits_count_pro <= 2": ["ess", "non_ess"]}, "ess"]}, {"hits_count_pro <= 2": [{"HFI_normalized <= 956": ["non_ess", "ess"]}, {"orf_len <= -0.6758462017229871": [{"NI <= 0.09172655565293597": ["non_ess", "ess"]}, "non_ess"]}]}]}]}, {"insertion_index <= 0.009237875288683604": [{"hits_count_pro <= 0": [{"insertion_index <= 0.008704061895551255": [{"NI <= 0.2939017504234896": [{"orf_len <= -0.31592987289125296": [{"HFI_normalized <= 154": ["ess", "non_ess"]}, {"reads_count <= -0.33512766394984056": ["ess", "non_ess"]}]}, "non_ess"]}, "ess"]}, {"HFI_normalized <= 258": [{"hits_count_pro <= 3": [{"HFI_normalized <= 190": ["non_ess", {"insertion_index <= 0.007194244604316547": ["non_ess", "ess"]}]}, "non_ess"]}, "non_ess"]}]}, {"hits_count_pro <= 0": [{"reads_count <= -0.33802800103206904": [{"orf_len <= -0.7958183113335652": [{"insertion_index <= 0.009345794392523364": ["non_ess", "ess"]}, "non_ess"]}, {"orf_len <= -0.18232456900674554": [{"orf_len <= -0.19595776328067488": ["non_ess", "ess"]}, "non_ess"]}]}, {"reads_count <= -0.35543002352543995": [{"reads_count <= -0.36123069768989696": ["non_ess", "ess"]}, "non_ess"]}]}]}]}]